{
  "schemaVersion": 1,
  "id": "canada-employment-relative-population-growth",
  "field": "canada_employment_relative_population_growth",
  "label": "Canada employment relative to working-age population growth",
  "description": "Growth in employment relative to the working-age population accounts for rapid population change.",
  "unit": "percent",
  "frequency": "monthly",
  "status": "measured",
  "layer": "Labour and households",
  "geography": "Canada",
  "geographyLevel": "national",
  "inputType": "domestic",
  "domesticOrExternal": "domestic",
  "directlyComparableAcrossCountries": false,
  "comparisonLimitations": "Definitions, currencies, industrial structure and release timing differ across countries.",
  "core": true,
  "interpretationDirection": "context-dependent",
  "interpretationLabel": "Direction unclear",
  "interpretation": "Growth in employment relative to the working-age population accounts for rapid population change.",
  "source": "Statistics Canada, table 14-10-0287-01",
  "sourceUrl": "https://www150.statcan.gc.ca/t1/tbl1/en/tv.action?pid=1410028701",
  "sourceIdentifier": "derived from v2062811, v2062809",
  "seasonalAdjustment": "seasonally adjusted",
  "nominalOrReal": "rate",
  "startDate": "1977-01-01",
  "endDate": "2026-06-01",
  "latest": {
    "date": "2026-06-01",
    "sourceDate": "2026-07-10",
    "value": -0.16325833081570762,
    "previousValue": 0.007977718974183645,
    "oneYearChange": 0.548813081033972,
    "threeMonthChange": 0.3076144475426701,
    "fourQuarterChange": 0.548813081033972,
    "historicalPercentile": 33.58585858585859,
    "percentileSince2000": 34.74842767295598,
    "distanceFromMedian": -0.48447581961765795,
    "momentum": "falling"
  },
  "referenceRanges": {
    "historicalMedian": 0.32121748880195033,
    "p10": -2.132924683734082,
    "p25": -0.43272783493041034,
    "p75": 1.2227905297708175,
    "p90": 1.9891615904572435,
    "minimum": -16.92284877875787,
    "maximum": 15.219770500988883
  },
  "observations": [
    {
      "date": "1977-01-01",
      "value": -0.06621321067992181,
      "sourceDate": "2018-06-08"
    },
    {
      "date": "1977-02-01",
      "value": -0.20506269487329254,
      "sourceDate": "2018-06-08"
    },
    {
      "date": "1977-03-01",
      "value": -0.6730561523087819,
      "sourceDate": "2018-06-08"
    },
    {
      "date": "1977-04-01",
      "value": -0.6927287238789326,
      "sourceDate": "2018-06-08"
    },
    {
      "date": "1977-05-01",
      "value": -0.35020698113219506,
      "sourceDate": "2018-06-08"
    },
    {
      "date": "1977-06-01",
      "value": -0.5588326460452264,
      "sourceDate": "2018-06-08"
    },
    {
      "date": "1977-07-01",
      "value": -0.5614850794160131,
      "sourceDate": "2018-06-08"
    },
    {
      "date": "1977-08-01",
      "value": -0.4997908973545462,
      "sourceDate": "2018-06-08"
    },
    {
      "date": "1977-09-01",
      "value": -0.6335879972711678,
      "sourceDate": "2018-06-08"
    },
    {
      "date": "1977-10-01",
      "value": -0.23787410265609932,
      "sourceDate": "2018-06-08"
    },
    {
      "date": "1977-11-01",
      "value": -0.5587897895336646,
      "sourceDate": "2018-06-08"
    },
    {
      "date": "1977-12-01",
      "value": -0.6282617385513722,
      "sourceDate": "2018-06-08"
    },
    {
      "date": "1978-01-01",
      "value": -0.5755657400892678,
      "sourceDate": "2018-06-08"
    },
    {
      "date": "1978-02-01",
      "value": -0.0724120739522327,
      "sourceDate": "2018-06-08"
    },
    {
      "date": "1978-03-01",
      "value": 0.3499847349856422,
      "sourceDate": "2018-06-08"
    },
    {
      "date": "1978-04-01",
      "value": 0.37323508931366156,
      "sourceDate": "2018-06-08"
    },
    {
      "date": "1978-05-01",
      "value": 0.362785372121488,
      "sourceDate": "2018-06-08"
    },
    {
      "date": "1978-06-01",
      "value": 1.0287745421766248,
      "sourceDate": "2018-06-08"
    },
    {
      "date": "1978-07-01",
      "value": 1.474376033709035,
      "sourceDate": "2018-06-08"
    },
    {
      "date": "1978-08-01",
      "value": 1.5605961442772154,
      "sourceDate": "2018-06-08"
    },
    {
      "date": "1978-09-01",
      "value": 1.7504720573868315,
      "sourceDate": "2018-06-08"
    },
    {
      "date": "1978-10-01",
      "value": 2.125045778867496,
      "sourceDate": "2018-06-08"
    },
    {
      "date": "1978-11-01",
      "value": 2.1710129385229315,
      "sourceDate": "2018-06-08"
    },
    {
      "date": "1978-12-01",
      "value": 2.31368329521211,
      "sourceDate": "2018-06-08"
    },
    {
      "date": "1979-01-01",
      "value": 2.742477661479481,
      "sourceDate": "2018-06-08"
    },
    {
      "date": "1979-02-01",
      "value": 2.255123155537997,
      "sourceDate": "2018-06-08"
    },
    {
      "date": "1979-03-01",
      "value": 2.372908223218584,
      "sourceDate": "2018-06-08"
    },
    {
      "date": "1979-04-01",
      "value": 2.299475478473778,
      "sourceDate": "2018-06-08"
    },
    {
      "date": "1979-05-01",
      "value": 2.658184561618948,
      "sourceDate": "2018-06-08"
    },
    {
      "date": "1979-06-01",
      "value": 2.3675000011203373,
      "sourceDate": "2018-06-08"
    },
    {
      "date": "1979-07-01",
      "value": 2.395027798129279,
      "sourceDate": "2018-06-08"
    },
    {
      "date": "1979-08-01",
      "value": 2.4813738070867064,
      "sourceDate": "2018-06-08"
    },
    {
      "date": "1979-09-01",
      "value": 2.432740403881528,
      "sourceDate": "2018-06-08"
    },
    {
      "date": "1979-10-01",
      "value": 2.248144292757237,
      "sourceDate": "2018-06-08"
    },
    {
      "date": "1979-11-01",
      "value": 2.3546387221715204,
      "sourceDate": "2018-06-08"
    },
    {
      "date": "1979-12-01",
      "value": 2.1082266921453874,
      "sourceDate": "2018-06-08"
    },
    {
      "date": "1980-01-01",
      "value": 1.7735432619469638,
      "sourceDate": "2018-06-08"
    },
    {
      "date": "1980-02-01",
      "value": 1.9119516547083215,
      "sourceDate": "2018-06-08"
    },
    {
      "date": "1980-03-01",
      "value": 1.4105728477291635,
      "sourceDate": "2018-06-08"
    },
    {
      "date": "1980-04-01",
      "value": 1.5466784155285573,
      "sourceDate": "2018-06-08"
    },
    {
      "date": "1980-05-01",
      "value": 0.6180302595355069,
      "sourceDate": "2018-06-08"
    },
    {
      "date": "1980-06-01",
      "value": 0.6624656470608503,
      "sourceDate": "2018-06-08"
    },
    {
      "date": "1980-07-01",
      "value": 0.14550797196433152,
      "sourceDate": "2018-06-08"
    },
    {
      "date": "1980-08-01",
      "value": 0.09828936668245802,
      "sourceDate": "2018-06-08"
    },
    {
      "date": "1980-09-01",
      "value": 0.6729463089885535,
      "sourceDate": "2018-06-08"
    },
    {
      "date": "1980-10-01",
      "value": 0.5200439787861777,
      "sourceDate": "2018-06-08"
    },
    {
      "date": "1980-11-01",
      "value": 0.6385315567356553,
      "sourceDate": "2018-06-08"
    },
    {
      "date": "1980-12-01",
      "value": 0.6049490216967879,
      "sourceDate": "2018-06-08"
    },
    {
      "date": "1981-01-01",
      "value": 1.0245270274590323,
      "sourceDate": "2018-06-08"
    },
    {
      "date": "1981-02-01",
      "value": 1.528839855476627,
      "sourceDate": "2018-06-08"
    },
    {
      "date": "1981-03-01",
      "value": 1.5546313055285088,
      "sourceDate": "2018-06-08"
    },
    {
      "date": "1981-04-01",
      "value": 1.5631131408234467,
      "sourceDate": "2018-06-08"
    },
    {
      "date": "1981-05-01",
      "value": 2.293755749203785,
      "sourceDate": "2018-06-08"
    },
    {
      "date": "1981-06-01",
      "value": 2.175928108457792,
      "sourceDate": "2018-06-08"
    },
    {
      "date": "1981-07-01",
      "value": 1.8653939604152292,
      "sourceDate": "2018-06-08"
    },
    {
      "date": "1981-08-01",
      "value": 1.719863193980431,
      "sourceDate": "2018-06-08"
    },
    {
      "date": "1981-09-01",
      "value": 0.7846280606139233,
      "sourceDate": "2018-06-08"
    },
    {
      "date": "1981-10-01",
      "value": 0.270358558649475,
      "sourceDate": "2018-06-08"
    },
    {
      "date": "1981-11-01",
      "value": -0.18208273816817666,
      "sourceDate": "2018-06-08"
    },
    {
      "date": "1981-12-01",
      "value": -0.7728124315578122,
      "sourceDate": "2018-06-08"
    },
    {
      "date": "1982-01-01",
      "value": -1.6125353321245761,
      "sourceDate": "2018-06-08"
    },
    {
      "date": "1982-02-01",
      "value": -2.5998612643425734,
      "sourceDate": "2018-06-08"
    },
    {
      "date": "1982-03-01",
      "value": -2.7762259340229245,
      "sourceDate": "2018-06-08"
    },
    {
      "date": "1982-04-01",
      "value": -3.636238525245916,
      "sourceDate": "2018-06-08"
    },
    {
      "date": "1982-05-01",
      "value": -4.348025664213395,
      "sourceDate": "2018-06-08"
    },
    {
      "date": "1982-06-01",
      "value": -5.285032608529705,
      "sourceDate": "2018-06-08"
    },
    {
      "date": "1982-07-01",
      "value": -5.347233419448472,
      "sourceDate": "2018-06-08"
    },
    {
      "date": "1982-08-01",
      "value": -6.001393002418565,
      "sourceDate": "2018-06-08"
    },
    {
      "date": "1982-09-01",
      "value": -6.010087957508537,
      "sourceDate": "2018-06-08"
    },
    {
      "date": "1982-10-01",
      "value": -5.9262866046040585,
      "sourceDate": "2018-06-08"
    },
    {
      "date": "1982-11-01",
      "value": -6.041885081238274,
      "sourceDate": "2018-06-08"
    },
    {
      "date": "1982-12-01",
      "value": -5.472214977484901,
      "sourceDate": "2018-06-08"
    },
    {
      "date": "1983-01-01",
      "value": -4.951657656845187,
      "sourceDate": "2018-06-08"
    },
    {
      "date": "1983-02-01",
      "value": -4.454110165577085,
      "sourceDate": "2018-06-08"
    },
    {
      "date": "1983-03-01",
      "value": -3.707229435260362,
      "sourceDate": "2018-06-08"
    },
    {
      "date": "1983-04-01",
      "value": -2.61958993653556,
      "sourceDate": "2018-06-08"
    },
    {
      "date": "1983-05-01",
      "value": -1.9653488986358214,
      "sourceDate": "2018-06-08"
    },
    {
      "date": "1983-06-01",
      "value": -0.5647954873879812,
      "sourceDate": "2018-06-08"
    },
    {
      "date": "1983-07-01",
      "value": 0.3506975303442461,
      "sourceDate": "2018-06-08"
    },
    {
      "date": "1983-08-01",
      "value": 1.3845080650009223,
      "sourceDate": "2018-06-08"
    },
    {
      "date": "1983-09-01",
      "value": 2.106914221567946,
      "sourceDate": "2018-06-08"
    },
    {
      "date": "1983-10-01",
      "value": 2.2025610579854638,
      "sourceDate": "2018-06-08"
    },
    {
      "date": "1983-11-01",
      "value": 2.4144529187974495,
      "sourceDate": "2018-06-08"
    },
    {
      "date": "1983-12-01",
      "value": 2.5577210779829995,
      "sourceDate": "2018-06-08"
    },
    {
      "date": "1984-01-01",
      "value": 2.1313747979371467,
      "sourceDate": "2018-06-08"
    },
    {
      "date": "1984-02-01",
      "value": 2.292636375676471,
      "sourceDate": "2018-06-08"
    },
    {
      "date": "1984-03-01",
      "value": 1.7817978434202075,
      "sourceDate": "2018-06-08"
    },
    {
      "date": "1984-04-01",
      "value": 1.1608651535217396,
      "sourceDate": "2018-06-08"
    },
    {
      "date": "1984-05-01",
      "value": 1.4231478601803405,
      "sourceDate": "2018-06-08"
    },
    {
      "date": "1984-06-01",
      "value": 1.4014518113435237,
      "sourceDate": "2018-06-08"
    },
    {
      "date": "1984-07-01",
      "value": 1.2688238053960799,
      "sourceDate": "2018-06-08"
    },
    {
      "date": "1984-08-01",
      "value": 0.7418727294803196,
      "sourceDate": "2018-06-08"
    },
    {
      "date": "1984-09-01",
      "value": 0.5279295391718231,
      "sourceDate": "2018-06-08"
    },
    {
      "date": "1984-10-01",
      "value": 0.7231307104969664,
      "sourceDate": "2018-06-08"
    },
    {
      "date": "1984-11-01",
      "value": 0.7682596826156463,
      "sourceDate": "2018-06-08"
    },
    {
      "date": "1984-12-01",
      "value": 0.8887133405809822,
      "sourceDate": "2018-06-08"
    },
    {
      "date": "1985-01-01",
      "value": 1.5154155006842585,
      "sourceDate": "2018-06-08"
    },
    {
      "date": "1985-02-01",
      "value": 1.4385023278884246,
      "sourceDate": "2018-06-08"
    },
    {
      "date": "1985-03-01",
      "value": 1.643302102253985,
      "sourceDate": "2018-06-08"
    },
    {
      "date": "1985-04-01",
      "value": 2.0640618021017465,
      "sourceDate": "2018-06-08"
    },
    {
      "date": "1985-05-01",
      "value": 2.010967798812313,
      "sourceDate": "2018-06-08"
    },
    {
      "date": "1985-06-01",
      "value": 1.5067447446315274,
      "sourceDate": "2018-06-08"
    },
    {
      "date": "1985-07-01",
      "value": 1.5999150949015162,
      "sourceDate": "2018-06-08"
    },
    {
      "date": "1985-08-01",
      "value": 1.9296150246733257,
      "sourceDate": "2018-06-08"
    },
    {
      "date": "1985-09-01",
      "value": 1.7752920352766877,
      "sourceDate": "2018-06-08"
    },
    {
      "date": "1985-10-01",
      "value": 1.9382804376287366,
      "sourceDate": "2018-06-08"
    },
    {
      "date": "1985-11-01",
      "value": 2.465443964023728,
      "sourceDate": "2018-06-08"
    },
    {
      "date": "1985-12-01",
      "value": 2.4711969004169054,
      "sourceDate": "2018-06-08"
    },
    {
      "date": "1986-01-01",
      "value": 2.374975236941168,
      "sourceDate": "2018-06-08"
    },
    {
      "date": "1986-02-01",
      "value": 2.280319746760906,
      "sourceDate": "2018-06-08"
    },
    {
      "date": "1986-03-01",
      "value": 2.1292495771048525,
      "sourceDate": "2018-06-08"
    },
    {
      "date": "1986-04-01",
      "value": 2.4687348370505457,
      "sourceDate": "2018-06-08"
    },
    {
      "date": "1986-05-01",
      "value": 1.8288547717001835,
      "sourceDate": "2018-06-08"
    },
    {
      "date": "1986-06-01",
      "value": 2.021326271844437,
      "sourceDate": "2018-06-08"
    },
    {
      "date": "1986-07-01",
      "value": 1.5793506316739148,
      "sourceDate": "2018-06-08"
    },
    {
      "date": "1986-08-01",
      "value": 1.3849382873415417,
      "sourceDate": "2018-06-08"
    },
    {
      "date": "1986-09-01",
      "value": 1.394779572356164,
      "sourceDate": "2018-06-08"
    },
    {
      "date": "1986-10-01",
      "value": 1.3448007088110447,
      "sourceDate": "2018-06-08"
    },
    {
      "date": "1986-11-01",
      "value": 0.9879263815883554,
      "sourceDate": "2018-06-08"
    },
    {
      "date": "1986-12-01",
      "value": 0.6160482220339603,
      "sourceDate": "2018-06-08"
    },
    {
      "date": "1987-01-01",
      "value": 0.4405464848279639,
      "sourceDate": "2018-06-08"
    },
    {
      "date": "1987-02-01",
      "value": 0.5366626971186284,
      "sourceDate": "2018-06-08"
    },
    {
      "date": "1987-03-01",
      "value": 0.8755728373826432,
      "sourceDate": "2018-06-08"
    },
    {
      "date": "1987-04-01",
      "value": 0.5959248888327995,
      "sourceDate": "2018-06-08"
    },
    {
      "date": "1987-05-01",
      "value": 1.3162246491343232,
      "sourceDate": "2018-06-08"
    },
    {
      "date": "1987-06-01",
      "value": 1.249128652677145,
      "sourceDate": "2018-06-08"
    },
    {
      "date": "1987-07-01",
      "value": 1.44764151951291,
      "sourceDate": "2018-06-08"
    },
    {
      "date": "1987-08-01",
      "value": 1.6248444260587025,
      "sourceDate": "2018-06-08"
    },
    {
      "date": "1987-09-01",
      "value": 1.8920803266678998,
      "sourceDate": "2018-06-08"
    },
    {
      "date": "1987-10-01",
      "value": 2.2158152881034843,
      "sourceDate": "2018-06-08"
    },
    {
      "date": "1987-11-01",
      "value": 2.2804339245981797,
      "sourceDate": "2018-06-08"
    },
    {
      "date": "1987-12-01",
      "value": 2.8227833455309437,
      "sourceDate": "2018-06-08"
    },
    {
      "date": "1988-01-01",
      "value": 2.788519703067549,
      "sourceDate": "2018-06-08"
    },
    {
      "date": "1988-02-01",
      "value": 2.8816394389425737,
      "sourceDate": "2018-06-08"
    },
    {
      "date": "1988-03-01",
      "value": 2.6231931231653682,
      "sourceDate": "2018-06-08"
    },
    {
      "date": "1988-04-01",
      "value": 2.3361158965458317,
      "sourceDate": "2018-06-08"
    },
    {
      "date": "1988-05-01",
      "value": 1.8708703940671478,
      "sourceDate": "2018-06-08"
    },
    {
      "date": "1988-06-01",
      "value": 1.7690763214889937,
      "sourceDate": "2018-06-08"
    },
    {
      "date": "1988-07-01",
      "value": 1.6618847339303189,
      "sourceDate": "2018-06-08"
    },
    {
      "date": "1988-08-01",
      "value": 1.4400834989168443,
      "sourceDate": "2018-06-08"
    },
    {
      "date": "1988-09-01",
      "value": 1.1928244405840394,
      "sourceDate": "2018-06-08"
    },
    {
      "date": "1988-10-01",
      "value": 0.9134896536423076,
      "sourceDate": "2018-06-08"
    },
    {
      "date": "1988-11-01",
      "value": 0.8952856522021602,
      "sourceDate": "2018-06-08"
    },
    {
      "date": "1988-12-01",
      "value": 0.7977974721954384,
      "sourceDate": "2018-06-08"
    },
    {
      "date": "1989-01-01",
      "value": 1.1884056236245444,
      "sourceDate": "2018-06-08"
    },
    {
      "date": "1989-02-01",
      "value": 0.9853929960187413,
      "sourceDate": "2018-06-08"
    },
    {
      "date": "1989-03-01",
      "value": 1.1684223223223933,
      "sourceDate": "2018-06-08"
    },
    {
      "date": "1989-04-01",
      "value": 0.8770066555001677,
      "sourceDate": "2018-06-08"
    },
    {
      "date": "1989-05-01",
      "value": 0.8522603688610131,
      "sourceDate": "2018-06-08"
    },
    {
      "date": "1989-06-01",
      "value": 0.8301018178554553,
      "sourceDate": "2018-06-08"
    },
    {
      "date": "1989-07-01",
      "value": 0.7125042081394195,
      "sourceDate": "2018-06-08"
    },
    {
      "date": "1989-08-01",
      "value": 1.0187317090987413,
      "sourceDate": "2018-06-08"
    },
    {
      "date": "1989-09-01",
      "value": 0.9092478056101028,
      "sourceDate": "2018-06-08"
    },
    {
      "date": "1989-10-01",
      "value": 0.652064951031428,
      "sourceDate": "2018-06-08"
    },
    {
      "date": "1989-11-01",
      "value": 0.5924289174014552,
      "sourceDate": "2018-06-08"
    },
    {
      "date": "1989-12-01",
      "value": 0.21963212026290257,
      "sourceDate": "2018-06-08"
    },
    {
      "date": "1990-01-01",
      "value": -0.06237820953588491,
      "sourceDate": "2018-06-08"
    },
    {
      "date": "1990-02-01",
      "value": 0.07470769669277733,
      "sourceDate": "2018-06-08"
    },
    {
      "date": "1990-03-01",
      "value": -0.3496460361915643,
      "sourceDate": "2018-06-08"
    },
    {
      "date": "1990-04-01",
      "value": -0.10862962198152637,
      "sourceDate": "2018-06-08"
    },
    {
      "date": "1990-05-01",
      "value": -0.40905345448810637,
      "sourceDate": "2018-06-08"
    },
    {
      "date": "1990-06-01",
      "value": -0.3071834208446256,
      "sourceDate": "2018-06-08"
    },
    {
      "date": "1990-07-01",
      "value": -0.5170022157237275,
      "sourceDate": "2018-06-08"
    },
    {
      "date": "1990-08-01",
      "value": -0.9767903225252561,
      "sourceDate": "2018-06-08"
    },
    {
      "date": "1990-09-01",
      "value": -1.0648100492850254,
      "sourceDate": "2018-06-08"
    },
    {
      "date": "1990-10-01",
      "value": -1.48175667403887,
      "sourceDate": "2018-06-08"
    },
    {
      "date": "1990-11-01",
      "value": -2.0861289034861064,
      "sourceDate": "2018-06-08"
    },
    {
      "date": "1990-12-01",
      "value": -2.5264047424661262,
      "sourceDate": "2018-06-08"
    },
    {
      "date": "1991-01-01",
      "value": -3.100474661983421,
      "sourceDate": "2018-06-08"
    },
    {
      "date": "1991-02-01",
      "value": -3.725843671016704,
      "sourceDate": "2018-06-08"
    },
    {
      "date": "1991-03-01",
      "value": -3.9355950841148846,
      "sourceDate": "2018-06-08"
    },
    {
      "date": "1991-04-01",
      "value": -3.7280980226549687,
      "sourceDate": "2018-06-08"
    },
    {
      "date": "1991-05-01",
      "value": -3.212290728563627,
      "sourceDate": "2018-06-08"
    },
    {
      "date": "1991-06-01",
      "value": -3.396041224673685,
      "sourceDate": "2018-06-08"
    },
    {
      "date": "1991-07-01",
      "value": -3.3006005579697795,
      "sourceDate": "2018-06-08"
    },
    {
      "date": "1991-08-01",
      "value": -3.1245258232562967,
      "sourceDate": "2018-06-08"
    },
    {
      "date": "1991-09-01",
      "value": -3.19280379418887,
      "sourceDate": "2018-06-08"
    },
    {
      "date": "1991-10-01",
      "value": -2.7236120040184164,
      "sourceDate": "2018-06-08"
    },
    {
      "date": "1991-11-01",
      "value": -2.596939753286631,
      "sourceDate": "2018-06-08"
    },
    {
      "date": "1991-12-01",
      "value": -2.3216722926923894,
      "sourceDate": "2018-06-08"
    },
    {
      "date": "1992-01-01",
      "value": -2.1529800181260716,
      "sourceDate": "2018-06-08"
    },
    {
      "date": "1992-02-01",
      "value": -1.8950565412529041,
      "sourceDate": "2018-06-08"
    },
    {
      "date": "1992-03-01",
      "value": -1.8390967007555936,
      "sourceDate": "2018-06-08"
    },
    {
      "date": "1992-04-01",
      "value": -2.2216418860300458,
      "sourceDate": "2018-06-08"
    },
    {
      "date": "1992-05-01",
      "value": -2.3873345091630416,
      "sourceDate": "2018-06-08"
    },
    {
      "date": "1992-06-01",
      "value": -2.59418547700202,
      "sourceDate": "2018-06-08"
    },
    {
      "date": "1992-07-01",
      "value": -2.3599069886872326,
      "sourceDate": "2018-06-08"
    },
    {
      "date": "1992-08-01",
      "value": -2.7086205514050055,
      "sourceDate": "2018-06-08"
    },
    {
      "date": "1992-09-01",
      "value": -2.514890119145141,
      "sourceDate": "2018-06-08"
    },
    {
      "date": "1992-10-01",
      "value": -2.468370616156934,
      "sourceDate": "2018-06-08"
    },
    {
      "date": "1992-11-01",
      "value": -2.2255994278333024,
      "sourceDate": "2018-06-08"
    },
    {
      "date": "1992-12-01",
      "value": -1.9685654335470093,
      "sourceDate": "2018-06-08"
    },
    {
      "date": "1993-01-01",
      "value": -1.5471167752812987,
      "sourceDate": "2018-06-08"
    },
    {
      "date": "1993-02-01",
      "value": -1.354944802438196,
      "sourceDate": "2018-06-08"
    },
    {
      "date": "1993-03-01",
      "value": -0.9787418917747037,
      "sourceDate": "2018-06-08"
    },
    {
      "date": "1993-04-01",
      "value": -1.1038371879012354,
      "sourceDate": "2018-06-08"
    },
    {
      "date": "1993-05-01",
      "value": -1.0777977634740865,
      "sourceDate": "2018-06-08"
    },
    {
      "date": "1993-06-01",
      "value": -0.7397768115547487,
      "sourceDate": "2018-06-08"
    },
    {
      "date": "1993-07-01",
      "value": -0.7780132444662802,
      "sourceDate": "2018-06-08"
    },
    {
      "date": "1993-08-01",
      "value": -0.3506735631557567,
      "sourceDate": "2018-06-08"
    },
    {
      "date": "1993-09-01",
      "value": -0.12259318634239014,
      "sourceDate": "2018-06-08"
    },
    {
      "date": "1993-10-01",
      "value": -0.3381765309389939,
      "sourceDate": "2018-06-08"
    },
    {
      "date": "1993-11-01",
      "value": 0.11010466743428537,
      "sourceDate": "2018-06-08"
    },
    {
      "date": "1993-12-01",
      "value": -0.2182440254837159,
      "sourceDate": "2018-06-08"
    },
    {
      "date": "1994-01-01",
      "value": -0.4036572429038987,
      "sourceDate": "2018-06-08"
    },
    {
      "date": "1994-02-01",
      "value": -0.21424869747208586,
      "sourceDate": "2018-06-08"
    },
    {
      "date": "1994-03-01",
      "value": -0.05372528988892844,
      "sourceDate": "2018-06-08"
    },
    {
      "date": "1994-04-01",
      "value": 0.27730602964799456,
      "sourceDate": "2018-06-08"
    },
    {
      "date": "1994-05-01",
      "value": 0.7359614231432721,
      "sourceDate": "2018-06-08"
    },
    {
      "date": "1994-06-01",
      "value": 0.7973028848508923,
      "sourceDate": "2018-06-08"
    },
    {
      "date": "1994-07-01",
      "value": 1.153168535271143,
      "sourceDate": "2018-06-08"
    },
    {
      "date": "1994-08-01",
      "value": 1.1233901117015277,
      "sourceDate": "2018-06-08"
    },
    {
      "date": "1994-09-01",
      "value": 1.3422053418880475,
      "sourceDate": "2018-06-08"
    },
    {
      "date": "1994-10-01",
      "value": 1.3966044817366852,
      "sourceDate": "2018-06-08"
    },
    {
      "date": "1994-11-01",
      "value": 1.697916745205208,
      "sourceDate": "2018-06-08"
    },
    {
      "date": "1994-12-01",
      "value": 1.7969800780070821,
      "sourceDate": "2018-06-08"
    },
    {
      "date": "1995-01-01",
      "value": 1.8797589225409306,
      "sourceDate": "2018-06-08"
    },
    {
      "date": "1995-02-01",
      "value": 1.571541761213302,
      "sourceDate": "2018-06-08"
    },
    {
      "date": "1995-03-01",
      "value": 1.480557488090728,
      "sourceDate": "2018-06-08"
    },
    {
      "date": "1995-04-01",
      "value": 1.218679482246765,
      "sourceDate": "2018-06-08"
    },
    {
      "date": "1995-05-01",
      "value": 0.6365022386045194,
      "sourceDate": "2018-06-08"
    },
    {
      "date": "1995-06-01",
      "value": 0.5036206517649466,
      "sourceDate": "2018-06-08"
    },
    {
      "date": "1995-07-01",
      "value": 0.08487973029107643,
      "sourceDate": "2018-06-08"
    },
    {
      "date": "1995-08-01",
      "value": 0.08908438672532437,
      "sourceDate": "2018-06-08"
    },
    {
      "date": "1995-09-01",
      "value": -0.1302760168086725,
      "sourceDate": "2018-06-08"
    },
    {
      "date": "1995-10-01",
      "value": 0.041158444442435105,
      "sourceDate": "2018-06-08"
    },
    {
      "date": "1995-11-01",
      "value": -0.884896076426267,
      "sourceDate": "2018-06-08"
    },
    {
      "date": "1995-12-01",
      "value": -0.4798965548570733,
      "sourceDate": "2018-06-08"
    },
    {
      "date": "1996-01-01",
      "value": -0.517351062328153,
      "sourceDate": "2018-06-08"
    },
    {
      "date": "1996-02-01",
      "value": -0.28816809646472485,
      "sourceDate": "2018-06-08"
    },
    {
      "date": "1996-03-01",
      "value": -0.668488883405105,
      "sourceDate": "2018-06-08"
    },
    {
      "date": "1996-04-01",
      "value": -0.3018300159140952,
      "sourceDate": "2018-06-08"
    },
    {
      "date": "1996-05-01",
      "value": -0.11507095079337226,
      "sourceDate": "2018-06-08"
    },
    {
      "date": "1996-06-01",
      "value": -0.2974368938728822,
      "sourceDate": "2018-06-08"
    },
    {
      "date": "1996-07-01",
      "value": -0.1340079088534507,
      "sourceDate": "2018-06-08"
    },
    {
      "date": "1996-08-01",
      "value": -0.1129823566761945,
      "sourceDate": "2018-06-08"
    },
    {
      "date": "1996-09-01",
      "value": -0.6981306340448801,
      "sourceDate": "2018-06-08"
    },
    {
      "date": "1996-10-01",
      "value": -0.817969272468555,
      "sourceDate": "2018-06-08"
    },
    {
      "date": "1996-11-01",
      "value": -0.360829940074503,
      "sourceDate": "2018-06-08"
    },
    {
      "date": "1996-12-01",
      "value": -0.4874430529377305,
      "sourceDate": "2018-06-08"
    },
    {
      "date": "1997-01-01",
      "value": -0.07917942287503088,
      "sourceDate": "2018-06-08"
    },
    {
      "date": "1997-02-01",
      "value": -0.23052029866588164,
      "sourceDate": "2018-06-08"
    },
    {
      "date": "1997-03-01",
      "value": 0.17988677875193648,
      "sourceDate": "2018-06-08"
    },
    {
      "date": "1997-04-01",
      "value": -0.032426720504075135,
      "sourceDate": "2018-06-08"
    },
    {
      "date": "1997-05-01",
      "value": 0.32349405473397486,
      "sourceDate": "2018-06-08"
    },
    {
      "date": "1997-06-01",
      "value": 0.7855625299986846,
      "sourceDate": "2018-06-08"
    },
    {
      "date": "1997-07-01",
      "value": 0.9188778308104384,
      "sourceDate": "2018-06-08"
    },
    {
      "date": "1997-08-01",
      "value": 1.2951602333776568,
      "sourceDate": "2018-06-08"
    },
    {
      "date": "1997-09-01",
      "value": 1.7370447978188208,
      "sourceDate": "2018-06-08"
    },
    {
      "date": "1997-10-01",
      "value": 1.8744190910074732,
      "sourceDate": "2018-06-08"
    },
    {
      "date": "1997-11-01",
      "value": 1.8538108624031935,
      "sourceDate": "2018-06-08"
    },
    {
      "date": "1997-12-01",
      "value": 1.789603961300834,
      "sourceDate": "2018-06-08"
    },
    {
      "date": "1998-01-01",
      "value": 1.1917897624557527,
      "sourceDate": "2018-06-08"
    },
    {
      "date": "1998-02-01",
      "value": 1.5308330558225558,
      "sourceDate": "2018-06-08"
    },
    {
      "date": "1998-03-01",
      "value": 1.5592724442673678,
      "sourceDate": "2018-06-08"
    },
    {
      "date": "1998-04-01",
      "value": 1.7881389700805217,
      "sourceDate": "2018-06-08"
    },
    {
      "date": "1998-05-01",
      "value": 1.4161093361514832,
      "sourceDate": "2018-06-08"
    },
    {
      "date": "1998-06-01",
      "value": 1.122689898093987,
      "sourceDate": "2018-06-08"
    },
    {
      "date": "1998-07-01",
      "value": 1.2499119124893765,
      "sourceDate": "2018-06-08"
    },
    {
      "date": "1998-08-01",
      "value": 1.0482085563948917,
      "sourceDate": "2018-06-08"
    },
    {
      "date": "1998-09-01",
      "value": 1.2241608789455016,
      "sourceDate": "2018-06-08"
    },
    {
      "date": "1998-10-01",
      "value": 1.2438008009302504,
      "sourceDate": "2018-06-08"
    },
    {
      "date": "1998-11-01",
      "value": 1.34199841383138,
      "sourceDate": "2018-06-08"
    },
    {
      "date": "1998-12-01",
      "value": 1.2425328960058435,
      "sourceDate": "2018-06-08"
    },
    {
      "date": "1999-01-01",
      "value": 1.8433247826320276,
      "sourceDate": "2018-06-08"
    },
    {
      "date": "1999-02-01",
      "value": 1.4111822575743727,
      "sourceDate": "2018-06-08"
    },
    {
      "date": "1999-03-01",
      "value": 1.259455855632985,
      "sourceDate": "2018-06-08"
    },
    {
      "date": "1999-04-01",
      "value": 1.3192573855585588,
      "sourceDate": "2018-06-08"
    },
    {
      "date": "1999-05-01",
      "value": 1.4545456508349153,
      "sourceDate": "2018-06-08"
    },
    {
      "date": "1999-06-01",
      "value": 1.4984002687568054,
      "sourceDate": "2018-06-08"
    },
    {
      "date": "1999-07-01",
      "value": 1.4717102339881771,
      "sourceDate": "2018-06-08"
    },
    {
      "date": "1999-08-01",
      "value": 1.3081593780525536,
      "sourceDate": "2018-06-08"
    },
    {
      "date": "1999-09-01",
      "value": 1.1910483994707288,
      "sourceDate": "2018-06-08"
    },
    {
      "date": "1999-10-01",
      "value": 1.3201051749947457,
      "sourceDate": "2018-06-08"
    },
    {
      "date": "1999-11-01",
      "value": 1.262096249735345,
      "sourceDate": "2018-06-08"
    },
    {
      "date": "1999-12-01",
      "value": 1.668088962375558,
      "sourceDate": "2018-06-08"
    },
    {
      "date": "2000-01-01",
      "value": 1.4277290049547142,
      "sourceDate": "2018-06-08"
    },
    {
      "date": "2000-02-01",
      "value": 1.6163505230590847,
      "sourceDate": "2018-06-08"
    },
    {
      "date": "2000-03-01",
      "value": 1.6667911485955145,
      "sourceDate": "2018-06-08"
    },
    {
      "date": "2000-04-01",
      "value": 1.557886913328943,
      "sourceDate": "2018-06-08"
    },
    {
      "date": "2000-05-01",
      "value": 1.355818787507168,
      "sourceDate": "2018-06-08"
    },
    {
      "date": "2000-06-01",
      "value": 1.2941394026187547,
      "sourceDate": "2018-06-08"
    },
    {
      "date": "2000-07-01",
      "value": 0.901045942362444,
      "sourceDate": "2018-06-08"
    },
    {
      "date": "2000-08-01",
      "value": 0.8741677741152643,
      "sourceDate": "2018-06-08"
    },
    {
      "date": "2000-09-01",
      "value": 0.9885189564462937,
      "sourceDate": "2018-06-08"
    },
    {
      "date": "2000-10-01",
      "value": 0.8550027655914505,
      "sourceDate": "2018-06-08"
    },
    {
      "date": "2000-11-01",
      "value": 0.8472912055272008,
      "sourceDate": "2018-06-08"
    },
    {
      "date": "2000-12-01",
      "value": 0.7357664558189647,
      "sourceDate": "2018-06-08"
    },
    {
      "date": "2001-01-01",
      "value": 0.3189409228699258,
      "sourceDate": "2018-06-08"
    },
    {
      "date": "2001-02-01",
      "value": 0.11886497481727876,
      "sourceDate": "2018-06-08"
    },
    {
      "date": "2001-03-01",
      "value": -0.030573921637155888,
      "sourceDate": "2018-06-08"
    },
    {
      "date": "2001-04-01",
      "value": -0.019416643509517773,
      "sourceDate": "2018-06-08"
    },
    {
      "date": "2001-05-01",
      "value": 0.0647177806479382,
      "sourceDate": "2018-06-08"
    },
    {
      "date": "2001-06-01",
      "value": -0.17677462724211557,
      "sourceDate": "2018-06-08"
    },
    {
      "date": "2001-07-01",
      "value": -0.07975910197185465,
      "sourceDate": "2021-01-25"
    },
    {
      "date": "2001-08-01",
      "value": -0.18357483417131837,
      "sourceDate": "2021-01-25"
    },
    {
      "date": "2001-09-01",
      "value": -0.30338518546976223,
      "sourceDate": "2021-01-25"
    },
    {
      "date": "2001-10-01",
      "value": -0.42656323257267426,
      "sourceDate": "2021-01-25"
    },
    {
      "date": "2001-11-01",
      "value": -0.5738475623340067,
      "sourceDate": "2021-01-25"
    },
    {
      "date": "2001-12-01",
      "value": -1.053955135425555,
      "sourceDate": "2021-01-25"
    },
    {
      "date": "2002-01-01",
      "value": -0.6076763772233762,
      "sourceDate": "2023-01-30"
    },
    {
      "date": "2002-02-01",
      "value": -0.3864534865941627,
      "sourceDate": "2023-01-30"
    },
    {
      "date": "2002-03-01",
      "value": 0.09791936531067247,
      "sourceDate": "2023-01-30"
    },
    {
      "date": "2002-04-01",
      "value": 0.18631851229704566,
      "sourceDate": "2023-01-30"
    },
    {
      "date": "2002-05-01",
      "value": 0.3858351340286337,
      "sourceDate": "2023-01-30"
    },
    {
      "date": "2002-06-01",
      "value": 0.9573008570071817,
      "sourceDate": "2023-01-30"
    },
    {
      "date": "2002-07-01",
      "value": 1.0658675187761313,
      "sourceDate": "2023-01-30"
    },
    {
      "date": "2002-08-01",
      "value": 1.6217714482648748,
      "sourceDate": "2023-01-30"
    },
    {
      "date": "2002-09-01",
      "value": 1.4492997854579803,
      "sourceDate": "2023-01-30"
    },
    {
      "date": "2002-10-01",
      "value": 1.5325460539054259,
      "sourceDate": "2023-01-30"
    },
    {
      "date": "2002-11-01",
      "value": 1.776879724629965,
      "sourceDate": "2023-01-30"
    },
    {
      "date": "2002-12-01",
      "value": 2.341639317288946,
      "sourceDate": "2023-01-30"
    },
    {
      "date": "2003-01-01",
      "value": 2.147997651298139,
      "sourceDate": "2023-01-30"
    },
    {
      "date": "2003-02-01",
      "value": 2.38896202132306,
      "sourceDate": "2023-01-30"
    },
    {
      "date": "2003-03-01",
      "value": 1.928503477128607,
      "sourceDate": "2023-01-30"
    },
    {
      "date": "2003-04-01",
      "value": 1.5291094758657975,
      "sourceDate": "2023-01-30"
    },
    {
      "date": "2003-05-01",
      "value": 1.0686182551793655,
      "sourceDate": "2023-01-30"
    },
    {
      "date": "2003-06-01",
      "value": 0.9878682734151267,
      "sourceDate": "2023-01-30"
    },
    {
      "date": "2003-07-01",
      "value": 0.8944964182430404,
      "sourceDate": "2023-01-30"
    },
    {
      "date": "2003-08-01",
      "value": 0.2811240880083776,
      "sourceDate": "2023-01-30"
    },
    {
      "date": "2003-09-01",
      "value": 0.5027221653280733,
      "sourceDate": "2023-01-30"
    },
    {
      "date": "2003-10-01",
      "value": 0.7510709199966215,
      "sourceDate": "2023-01-30"
    },
    {
      "date": "2003-11-01",
      "value": 0.7417227639086033,
      "sourceDate": "2023-01-30"
    },
    {
      "date": "2003-12-01",
      "value": 0.633411283575791,
      "sourceDate": "2023-01-30"
    },
    {
      "date": "2004-01-01",
      "value": 0.49345945340664166,
      "sourceDate": "2023-01-30"
    },
    {
      "date": "2004-02-01",
      "value": 0.1489664247785072,
      "sourceDate": "2023-01-30"
    },
    {
      "date": "2004-03-01",
      "value": 0.1517804795247102,
      "sourceDate": "2023-01-30"
    },
    {
      "date": "2004-04-01",
      "value": 0.5681963958314329,
      "sourceDate": "2023-01-30"
    },
    {
      "date": "2004-05-01",
      "value": 0.7909578397278239,
      "sourceDate": "2023-01-30"
    },
    {
      "date": "2004-06-01",
      "value": 0.587585958120096,
      "sourceDate": "2023-01-30"
    },
    {
      "date": "2004-07-01",
      "value": 0.5293997130053851,
      "sourceDate": "2023-01-30"
    },
    {
      "date": "2004-08-01",
      "value": 0.6054590681286331,
      "sourceDate": "2023-01-30"
    },
    {
      "date": "2004-09-01",
      "value": 0.6076180630077976,
      "sourceDate": "2023-01-30"
    },
    {
      "date": "2004-10-01",
      "value": 0.323614430164354,
      "sourceDate": "2023-01-30"
    },
    {
      "date": "2004-11-01",
      "value": 0.13145436181525305,
      "sourceDate": "2023-01-30"
    },
    {
      "date": "2004-12-01",
      "value": -0.050875712971309994,
      "sourceDate": "2023-01-30"
    },
    {
      "date": "2005-01-01",
      "value": 0.02558724828551906,
      "sourceDate": "2023-01-30"
    },
    {
      "date": "2005-02-01",
      "value": 0.05728419770560933,
      "sourceDate": "2023-01-30"
    },
    {
      "date": "2005-03-01",
      "value": -0.008768343199161421,
      "sourceDate": "2023-01-30"
    },
    {
      "date": "2005-04-01",
      "value": -0.14188961210351847,
      "sourceDate": "2023-01-30"
    },
    {
      "date": "2005-05-01",
      "value": -0.26232576047575673,
      "sourceDate": "2023-01-30"
    },
    {
      "date": "2005-06-01",
      "value": -0.23032816346857388,
      "sourceDate": "2023-01-30"
    },
    {
      "date": "2005-07-01",
      "value": -0.07839447045479009,
      "sourceDate": "2023-01-30"
    },
    {
      "date": "2005-08-01",
      "value": 0.13414058706127108,
      "sourceDate": "2023-01-30"
    },
    {
      "date": "2005-09-01",
      "value": -0.1697979961669538,
      "sourceDate": "2023-01-30"
    },
    {
      "date": "2005-10-01",
      "value": 0.0018874644955868547,
      "sourceDate": "2023-01-30"
    },
    {
      "date": "2005-11-01",
      "value": 0.05535225641983832,
      "sourceDate": "2023-01-30"
    },
    {
      "date": "2005-12-01",
      "value": -0.09451546939782673,
      "sourceDate": "2023-01-30"
    },
    {
      "date": "2006-01-01",
      "value": -0.021482608868250708,
      "sourceDate": "2023-01-30"
    },
    {
      "date": "2006-02-01",
      "value": 0.09975504444963423,
      "sourceDate": "2023-01-30"
    },
    {
      "date": "2006-03-01",
      "value": 0.4404661247056296,
      "sourceDate": "2023-01-30"
    },
    {
      "date": "2006-04-01",
      "value": 0.4970492269867677,
      "sourceDate": "2023-01-30"
    },
    {
      "date": "2006-05-01",
      "value": 0.8787875275352075,
      "sourceDate": "2023-01-30"
    },
    {
      "date": "2006-06-01",
      "value": 0.6144810375184218,
      "sourceDate": "2023-01-30"
    },
    {
      "date": "2006-07-01",
      "value": 0.41580934067306785,
      "sourceDate": "2023-01-30"
    },
    {
      "date": "2006-08-01",
      "value": 0.11576167796853998,
      "sourceDate": "2023-01-30"
    },
    {
      "date": "2006-09-01",
      "value": 0.4030342506561757,
      "sourceDate": "2023-01-30"
    },
    {
      "date": "2006-10-01",
      "value": 0.2792738232374914,
      "sourceDate": "2023-01-30"
    },
    {
      "date": "2006-11-01",
      "value": 0.1001191387605127,
      "sourceDate": "2023-01-30"
    },
    {
      "date": "2006-12-01",
      "value": 0.5312668990796299,
      "sourceDate": "2023-01-30"
    },
    {
      "date": "2007-01-01",
      "value": 0.7737127795105714,
      "sourceDate": "2023-01-30"
    },
    {
      "date": "2007-02-01",
      "value": 0.7296069619813883,
      "sourceDate": "2023-01-30"
    },
    {
      "date": "2007-03-01",
      "value": 0.5774388830190436,
      "sourceDate": "2023-01-30"
    },
    {
      "date": "2007-04-01",
      "value": 0.3117919610891473,
      "sourceDate": "2023-01-30"
    },
    {
      "date": "2007-05-01",
      "value": 0.0865231483048845,
      "sourceDate": "2023-01-30"
    },
    {
      "date": "2007-06-01",
      "value": 0.4812503846211902,
      "sourceDate": "2023-01-30"
    },
    {
      "date": "2007-07-01",
      "value": 0.8241836969955951,
      "sourceDate": "2025-01-24"
    },
    {
      "date": "2007-08-01",
      "value": 1.0102633768548586,
      "sourceDate": "2025-01-24"
    },
    {
      "date": "2007-09-01",
      "value": 0.9245428241673181,
      "sourceDate": "2025-01-24"
    },
    {
      "date": "2007-10-01",
      "value": 1.08561851082154,
      "sourceDate": "2025-01-24"
    },
    {
      "date": "2007-11-01",
      "value": 1.2094672472593437,
      "sourceDate": "2025-01-24"
    },
    {
      "date": "2007-12-01",
      "value": 0.843138093546747,
      "sourceDate": "2025-01-24"
    },
    {
      "date": "2008-01-01",
      "value": 0.592965769563647,
      "sourceDate": "2025-01-24"
    },
    {
      "date": "2008-02-01",
      "value": 0.6612133038346624,
      "sourceDate": "2025-01-24"
    },
    {
      "date": "2008-03-01",
      "value": 0.5064572510904419,
      "sourceDate": "2025-01-24"
    },
    {
      "date": "2008-04-01",
      "value": 0.5335123461827962,
      "sourceDate": "2025-01-24"
    },
    {
      "date": "2008-05-01",
      "value": 0.47188960265422963,
      "sourceDate": "2025-01-24"
    },
    {
      "date": "2008-06-01",
      "value": 0.21233622648888506,
      "sourceDate": "2025-01-24"
    },
    {
      "date": "2008-07-01",
      "value": -0.2683084326988494,
      "sourceDate": "2025-01-24"
    },
    {
      "date": "2008-08-01",
      "value": -0.2649916115318729,
      "sourceDate": "2025-01-24"
    },
    {
      "date": "2008-09-01",
      "value": -0.27146129732412705,
      "sourceDate": "2025-01-24"
    },
    {
      "date": "2008-10-01",
      "value": -0.2911669082947932,
      "sourceDate": "2025-01-24"
    },
    {
      "date": "2008-11-01",
      "value": -0.9285976478615843,
      "sourceDate": "2025-01-24"
    },
    {
      "date": "2008-12-01",
      "value": -1.004725381915983,
      "sourceDate": "2025-01-24"
    },
    {
      "date": "2009-01-01",
      "value": -2.001257811844104,
      "sourceDate": "2025-01-24"
    },
    {
      "date": "2009-02-01",
      "value": -2.47178394939378,
      "sourceDate": "2025-01-24"
    },
    {
      "date": "2009-03-01",
      "value": -2.6536217091705505,
      "sourceDate": "2025-01-24"
    },
    {
      "date": "2009-04-01",
      "value": -2.785625219837007,
      "sourceDate": "2025-01-24"
    },
    {
      "date": "2009-05-01",
      "value": -2.816394719991211,
      "sourceDate": "2025-01-24"
    },
    {
      "date": "2009-06-01",
      "value": -3.0330588343388865,
      "sourceDate": "2025-01-24"
    },
    {
      "date": "2009-07-01",
      "value": -3.000066787542921,
      "sourceDate": "2025-01-24"
    },
    {
      "date": "2009-08-01",
      "value": -3.129329058471686,
      "sourceDate": "2025-01-24"
    },
    {
      "date": "2009-09-01",
      "value": -3.0187350812374003,
      "sourceDate": "2025-01-24"
    },
    {
      "date": "2009-10-01",
      "value": -3.2160995638872314,
      "sourceDate": "2025-01-24"
    },
    {
      "date": "2009-11-01",
      "value": -2.2932719252295786,
      "sourceDate": "2025-01-24"
    },
    {
      "date": "2009-12-01",
      "value": -2.3821686357234584,
      "sourceDate": "2025-01-24"
    },
    {
      "date": "2010-01-01",
      "value": -1.3586513312442539,
      "sourceDate": "2025-01-24"
    },
    {
      "date": "2010-02-01",
      "value": -1.1431770019952658,
      "sourceDate": "2025-01-24"
    },
    {
      "date": "2010-03-01",
      "value": -0.7299907988451038,
      "sourceDate": "2025-01-24"
    },
    {
      "date": "2010-04-01",
      "value": -0.18161804475286258,
      "sourceDate": "2025-01-24"
    },
    {
      "date": "2010-05-01",
      "value": -0.1305096994774546,
      "sourceDate": "2025-01-24"
    },
    {
      "date": "2010-06-01",
      "value": 0.49884382767726443,
      "sourceDate": "2025-01-24"
    },
    {
      "date": "2010-07-01",
      "value": 0.6270706053554065,
      "sourceDate": "2025-01-24"
    },
    {
      "date": "2010-08-01",
      "value": 0.7604446554068334,
      "sourceDate": "2025-01-24"
    },
    {
      "date": "2010-09-01",
      "value": 0.5273541260796488,
      "sourceDate": "2025-01-24"
    },
    {
      "date": "2010-10-01",
      "value": 0.3992502117417196,
      "sourceDate": "2025-01-24"
    },
    {
      "date": "2010-11-01",
      "value": 0.2473089807188078,
      "sourceDate": "2025-01-24"
    },
    {
      "date": "2010-12-01",
      "value": 0.5824303456010815,
      "sourceDate": "2025-01-24"
    },
    {
      "date": "2011-01-01",
      "value": 0.8456035075915302,
      "sourceDate": "2025-01-24"
    },
    {
      "date": "2011-02-01",
      "value": 0.8379043335111191,
      "sourceDate": "2025-01-24"
    },
    {
      "date": "2011-03-01",
      "value": 0.5913436816284312,
      "sourceDate": "2025-01-24"
    },
    {
      "date": "2011-04-01",
      "value": 0.49656146087886377,
      "sourceDate": "2025-01-24"
    },
    {
      "date": "2011-05-01",
      "value": 0.18752784251085952,
      "sourceDate": "2025-01-24"
    },
    {
      "date": "2011-06-01",
      "value": -0.028262982131477266,
      "sourceDate": "2025-01-24"
    },
    {
      "date": "2011-07-01",
      "value": 0.14444818464611764,
      "sourceDate": "2025-01-24"
    },
    {
      "date": "2011-08-01",
      "value": 0.08218225514695643,
      "sourceDate": "2025-01-24"
    },
    {
      "date": "2011-09-01",
      "value": 0.12583391785714326,
      "sourceDate": "2025-01-24"
    },
    {
      "date": "2011-10-01",
      "value": 0.13279549387610334,
      "sourceDate": "2025-01-24"
    },
    {
      "date": "2011-11-01",
      "value": -0.22833760635597722,
      "sourceDate": "2025-01-24"
    },
    {
      "date": "2011-12-01",
      "value": -0.2992853450734634,
      "sourceDate": "2025-01-24"
    },
    {
      "date": "2012-01-01",
      "value": -0.6468924576811141,
      "sourceDate": "2025-01-24"
    },
    {
      "date": "2012-02-01",
      "value": -0.7265322557969411,
      "sourceDate": "2025-01-24"
    },
    {
      "date": "2012-03-01",
      "value": -0.18675940247125933,
      "sourceDate": "2025-01-24"
    },
    {
      "date": "2012-04-01",
      "value": -0.05025039528083752,
      "sourceDate": "2025-01-24"
    },
    {
      "date": "2012-05-01",
      "value": 0.14299661034284927,
      "sourceDate": "2025-01-24"
    },
    {
      "date": "2012-06-01",
      "value": -0.04373249619140651,
      "sourceDate": "2025-01-24"
    },
    {
      "date": "2012-07-01",
      "value": -0.14913669601982482,
      "sourceDate": "2025-01-24"
    },
    {
      "date": "2012-08-01",
      "value": 0.07689584965904217,
      "sourceDate": "2025-01-24"
    },
    {
      "date": "2012-09-01",
      "value": 0.34969882422306586,
      "sourceDate": "2025-01-24"
    },
    {
      "date": "2012-10-01",
      "value": 0.4816263886184613,
      "sourceDate": "2025-01-24"
    },
    {
      "date": "2012-11-01",
      "value": 0.6982062000870703,
      "sourceDate": "2025-01-24"
    },
    {
      "date": "2012-12-01",
      "value": 0.8678984714041604,
      "sourceDate": "2025-01-24"
    },
    {
      "date": "2013-01-01",
      "value": 0.7497594351308479,
      "sourceDate": "2025-01-24"
    },
    {
      "date": "2013-02-01",
      "value": 1.3563947126408626,
      "sourceDate": "2025-01-24"
    },
    {
      "date": "2013-03-01",
      "value": 0.4380122452493751,
      "sourceDate": "2025-01-24"
    },
    {
      "date": "2013-04-01",
      "value": 0.16832308615064573,
      "sourceDate": "2025-01-24"
    },
    {
      "date": "2013-05-01",
      "value": 0.48286092166245353,
      "sourceDate": "2025-01-24"
    },
    {
      "date": "2013-06-01",
      "value": 0.4148017481514277,
      "sourceDate": "2025-01-24"
    },
    {
      "date": "2013-07-01",
      "value": 0.10007593107197454,
      "sourceDate": "2025-01-24"
    },
    {
      "date": "2013-08-01",
      "value": -0.0019894407701670502,
      "sourceDate": "2025-01-24"
    },
    {
      "date": "2013-09-01",
      "value": -0.3965546970603695,
      "sourceDate": "2025-01-24"
    },
    {
      "date": "2013-10-01",
      "value": -0.40817048708655657,
      "sourceDate": "2025-01-24"
    },
    {
      "date": "2013-11-01",
      "value": -0.3600404671242452,
      "sourceDate": "2025-01-24"
    },
    {
      "date": "2013-12-01",
      "value": -0.7332304132268708,
      "sourceDate": "2025-01-24"
    },
    {
      "date": "2014-01-01",
      "value": -0.6773493243033224,
      "sourceDate": "2025-01-24"
    },
    {
      "date": "2014-02-01",
      "value": -1.1217999743217355,
      "sourceDate": "2025-01-24"
    },
    {
      "date": "2014-03-01",
      "value": -0.5454528290812499,
      "sourceDate": "2025-01-24"
    },
    {
      "date": "2014-04-01",
      "value": -0.756856331701039,
      "sourceDate": "2025-01-24"
    },
    {
      "date": "2014-05-01",
      "value": -1.058164799988437,
      "sourceDate": "2025-01-24"
    },
    {
      "date": "2014-06-01",
      "value": -0.8311628737505239,
      "sourceDate": "2025-01-24"
    },
    {
      "date": "2014-07-01",
      "value": -0.3312198333070948,
      "sourceDate": "2025-01-24"
    },
    {
      "date": "2014-08-01",
      "value": -0.7439511897952555,
      "sourceDate": "2025-01-24"
    },
    {
      "date": "2014-09-01",
      "value": -0.4345712768868637,
      "sourceDate": "2025-01-24"
    },
    {
      "date": "2014-10-01",
      "value": -0.28812717809932886,
      "sourceDate": "2025-01-24"
    },
    {
      "date": "2014-11-01",
      "value": -0.4082768884916099,
      "sourceDate": "2025-01-24"
    },
    {
      "date": "2014-12-01",
      "value": -0.05589144359496867,
      "sourceDate": "2025-01-24"
    },
    {
      "date": "2015-01-01",
      "value": -0.05797284784441192,
      "sourceDate": "2025-01-24"
    },
    {
      "date": "2015-02-01",
      "value": 0.062309792656489726,
      "sourceDate": "2025-01-24"
    },
    {
      "date": "2015-03-01",
      "value": 0.03487126453984857,
      "sourceDate": "2025-01-24"
    },
    {
      "date": "2015-04-01",
      "value": -0.06967044004445588,
      "sourceDate": "2025-01-24"
    },
    {
      "date": "2015-05-01",
      "value": 0.1102375117671972,
      "sourceDate": "2025-01-24"
    },
    {
      "date": "2015-06-01",
      "value": -0.09548657747663336,
      "sourceDate": "2025-01-24"
    },
    {
      "date": "2015-07-01",
      "value": -0.23590709929105502,
      "sourceDate": "2025-01-24"
    },
    {
      "date": "2015-08-01",
      "value": 0.16194090960242047,
      "sourceDate": "2025-01-24"
    },
    {
      "date": "2015-09-01",
      "value": -0.042165578579134166,
      "sourceDate": "2025-01-24"
    },
    {
      "date": "2015-10-01",
      "value": -0.166093764606845,
      "sourceDate": "2025-01-24"
    },
    {
      "date": "2015-11-01",
      "value": -0.34343261469093056,
      "sourceDate": "2025-01-24"
    },
    {
      "date": "2015-12-01",
      "value": -0.6004019556707263,
      "sourceDate": "2025-01-24"
    },
    {
      "date": "2016-01-01",
      "value": -0.57980510618032,
      "sourceDate": "2025-01-24"
    },
    {
      "date": "2016-02-01",
      "value": -0.6256096379137044,
      "sourceDate": "2025-01-24"
    },
    {
      "date": "2016-03-01",
      "value": -0.7842364181025019,
      "sourceDate": "2025-01-24"
    },
    {
      "date": "2016-04-01",
      "value": -0.46167446875927665,
      "sourceDate": "2025-01-24"
    },
    {
      "date": "2016-05-01",
      "value": -0.49311174094739396,
      "sourceDate": "2025-01-24"
    },
    {
      "date": "2016-06-01",
      "value": -0.42719750906105025,
      "sourceDate": "2025-01-24"
    },
    {
      "date": "2016-07-01",
      "value": -0.6678575396770525,
      "sourceDate": "2025-01-24"
    },
    {
      "date": "2016-08-01",
      "value": -0.5641743599796856,
      "sourceDate": "2025-01-24"
    },
    {
      "date": "2016-09-01",
      "value": -0.3546556171465598,
      "sourceDate": "2025-01-24"
    },
    {
      "date": "2016-10-01",
      "value": -0.3145624057531604,
      "sourceDate": "2025-01-24"
    },
    {
      "date": "2016-11-01",
      "value": -0.044698055314129626,
      "sourceDate": "2025-01-24"
    },
    {
      "date": "2016-12-01",
      "value": 0.1272111126425557,
      "sourceDate": "2025-01-24"
    },
    {
      "date": "2017-01-01",
      "value": 0.45730066532867486,
      "sourceDate": "2025-01-24"
    },
    {
      "date": "2017-02-01",
      "value": 0.6207193480326278,
      "sourceDate": "2025-01-24"
    },
    {
      "date": "2017-03-01",
      "value": 0.7154434435136192,
      "sourceDate": "2025-01-24"
    },
    {
      "date": "2017-04-01",
      "value": 0.7067691489649475,
      "sourceDate": "2025-01-24"
    },
    {
      "date": "2017-05-01",
      "value": 0.7604062856879201,
      "sourceDate": "2025-01-24"
    },
    {
      "date": "2017-06-01",
      "value": 1.0372572968962768,
      "sourceDate": "2025-01-24"
    },
    {
      "date": "2017-07-01",
      "value": 1.3456307168123738,
      "sourceDate": "2025-01-24"
    },
    {
      "date": "2017-08-01",
      "value": 1.1357437629064604,
      "sourceDate": "2025-01-24"
    },
    {
      "date": "2017-09-01",
      "value": 0.9376887105362997,
      "sourceDate": "2025-01-24"
    },
    {
      "date": "2017-10-01",
      "value": 0.9909491609781274,
      "sourceDate": "2025-01-24"
    },
    {
      "date": "2017-11-01",
      "value": 1.241451989870579,
      "sourceDate": "2025-01-24"
    },
    {
      "date": "2017-12-01",
      "value": 1.4383500235826574,
      "sourceDate": "2025-01-24"
    },
    {
      "date": "2018-01-01",
      "value": 0.788719471022481,
      "sourceDate": "2025-01-24"
    },
    {
      "date": "2018-02-01",
      "value": 0.49370232260115277,
      "sourceDate": "2025-01-24"
    },
    {
      "date": "2018-03-01",
      "value": 0.661796207686649,
      "sourceDate": "2025-01-24"
    },
    {
      "date": "2018-04-01",
      "value": 0.35225944895409533,
      "sourceDate": "2025-01-24"
    },
    {
      "date": "2018-05-01",
      "value": 0.1784236995752142,
      "sourceDate": "2025-01-24"
    },
    {
      "date": "2018-06-01",
      "value": 0.13935144541881161,
      "sourceDate": "2025-01-24"
    },
    {
      "date": "2018-07-01",
      "value": 0.31819385671139067,
      "sourceDate": "2025-01-24"
    },
    {
      "date": "2018-08-01",
      "value": -0.058854494803428636,
      "sourceDate": "2025-01-24"
    },
    {
      "date": "2018-09-01",
      "value": 0.41310693638678675,
      "sourceDate": "2025-01-24"
    },
    {
      "date": "2018-10-01",
      "value": 0.335341803896938,
      "sourceDate": "2025-01-24"
    },
    {
      "date": "2018-11-01",
      "value": 0.22946839444668576,
      "sourceDate": "2025-01-24"
    },
    {
      "date": "2018-12-01",
      "value": -0.0035110253516656975,
      "sourceDate": "2025-01-24"
    },
    {
      "date": "2019-01-01",
      "value": 0.40748246853861136,
      "sourceDate": "2025-01-24"
    },
    {
      "date": "2019-02-01",
      "value": 0.7098367671917849,
      "sourceDate": "2025-01-24"
    },
    {
      "date": "2019-03-01",
      "value": 0.2426397632769639,
      "sourceDate": "2025-01-24"
    },
    {
      "date": "2019-04-01",
      "value": 1.0032266608414275,
      "sourceDate": "2025-01-24"
    },
    {
      "date": "2019-05-01",
      "value": 1.04473258106903,
      "sourceDate": "2025-01-24"
    },
    {
      "date": "2019-06-01",
      "value": 0.811401290760716,
      "sourceDate": "2025-01-24"
    },
    {
      "date": "2019-07-01",
      "value": 0.2897174655048351,
      "sourceDate": "2025-01-24"
    },
    {
      "date": "2019-08-01",
      "value": 0.8912143602819445,
      "sourceDate": "2025-01-24"
    },
    {
      "date": "2019-09-01",
      "value": 0.3717047221715175,
      "sourceDate": "2025-01-24"
    },
    {
      "date": "2019-10-01",
      "value": 0.17868720661597948,
      "sourceDate": "2025-01-24"
    },
    {
      "date": "2019-11-01",
      "value": -0.3244855783809508,
      "sourceDate": "2025-01-24"
    },
    {
      "date": "2019-12-01",
      "value": -0.00878410048829048,
      "sourceDate": "2025-01-24"
    },
    {
      "date": "2020-01-01",
      "value": -0.07264233553978539,
      "sourceDate": "2025-01-24"
    },
    {
      "date": "2020-02-01",
      "value": -0.3663165797006762,
      "sourceDate": "2025-01-24"
    },
    {
      "date": "2020-03-01",
      "value": -6.18513049182341,
      "sourceDate": "2025-01-24"
    },
    {
      "date": "2020-04-01",
      "value": -16.92284877875787,
      "sourceDate": "2025-01-24"
    },
    {
      "date": "2020-05-01",
      "value": -15.27266728954676,
      "sourceDate": "2025-01-24"
    },
    {
      "date": "2020-06-01",
      "value": -9.8423595367642,
      "sourceDate": "2025-01-24"
    },
    {
      "date": "2020-07-01",
      "value": -7.530760518616486,
      "sourceDate": "2025-01-24"
    },
    {
      "date": "2020-08-01",
      "value": -6.56449092058028,
      "sourceDate": "2025-01-24"
    },
    {
      "date": "2020-09-01",
      "value": -4.331626048481352,
      "sourceDate": "2025-01-24"
    },
    {
      "date": "2020-10-01",
      "value": -3.877174057093258,
      "sourceDate": "2025-01-24"
    },
    {
      "date": "2020-11-01",
      "value": -3.4463538586731013,
      "sourceDate": "2025-01-24"
    },
    {
      "date": "2020-12-01",
      "value": -4.109052995955754,
      "sourceDate": "2025-01-24"
    },
    {
      "date": "2021-01-01",
      "value": -5.141559073833468,
      "sourceDate": "2025-01-24"
    },
    {
      "date": "2021-02-01",
      "value": -3.833188404125354,
      "sourceDate": "2025-01-24"
    },
    {
      "date": "2021-03-01",
      "value": 3.6846295502209747,
      "sourceDate": "2025-01-24"
    },
    {
      "date": "2021-04-01",
      "value": 15.219770500988883,
      "sourceDate": "2025-01-24"
    },
    {
      "date": "2021-05-01",
      "value": 12.675664996189528,
      "sourceDate": "2025-01-24"
    },
    {
      "date": "2021-06-01",
      "value": 7.408014641534644,
      "sourceDate": "2025-01-24"
    },
    {
      "date": "2021-07-01",
      "value": 5.5224386128740255,
      "sourceDate": "2025-01-24"
    },
    {
      "date": "2021-08-01",
      "value": 4.469667268257593,
      "sourceDate": "2025-01-24"
    },
    {
      "date": "2021-09-01",
      "value": 2.9580001259779998,
      "sourceDate": "2025-01-24"
    },
    {
      "date": "2021-10-01",
      "value": 2.7501083439384955,
      "sourceDate": "2025-01-24"
    },
    {
      "date": "2021-11-01",
      "value": 3.260882908611462,
      "sourceDate": "2025-01-24"
    },
    {
      "date": "2021-12-01",
      "value": 3.850189253165004,
      "sourceDate": "2025-01-24"
    },
    {
      "date": "2022-01-01",
      "value": 3.783335500411966,
      "sourceDate": "2025-01-24"
    },
    {
      "date": "2022-02-01",
      "value": 4.088817215547946,
      "sourceDate": "2025-01-24"
    },
    {
      "date": "2022-03-01",
      "value": 2.7679143510859427,
      "sourceDate": "2025-01-24"
    },
    {
      "date": "2022-04-01",
      "value": 4.0968950016696315,
      "sourceDate": "2025-01-24"
    },
    {
      "date": "2022-05-01",
      "value": 4.539083263575572,
      "sourceDate": "2025-01-24"
    },
    {
      "date": "2022-06-01",
      "value": 2.907096481451865,
      "sourceDate": "2025-01-24"
    },
    {
      "date": "2022-07-01",
      "value": 2.3693978887172618,
      "sourceDate": "2026-01-26"
    },
    {
      "date": "2022-08-01",
      "value": 1.9285180577470529,
      "sourceDate": "2026-01-26"
    },
    {
      "date": "2022-09-01",
      "value": 1.0436800898252052,
      "sourceDate": "2026-01-26"
    },
    {
      "date": "2022-10-01",
      "value": 1.2390020375661726,
      "sourceDate": "2026-01-26"
    },
    {
      "date": "2022-11-01",
      "value": 0.6395034242978159,
      "sourceDate": "2026-01-26"
    },
    {
      "date": "2022-12-01",
      "value": 0.6174410559125931,
      "sourceDate": "2026-01-26"
    },
    {
      "date": "2023-01-01",
      "value": 2.0702849930361644,
      "sourceDate": "2026-01-26"
    },
    {
      "date": "2023-02-01",
      "value": 0.4891933206890853,
      "sourceDate": "2026-01-26"
    },
    {
      "date": "2023-03-01",
      "value": 0.6174344699908962,
      "sourceDate": "2026-01-26"
    },
    {
      "date": "2023-04-01",
      "value": 0.3294141606402068,
      "sourceDate": "2026-01-26"
    },
    {
      "date": "2023-05-01",
      "value": -0.01176424247280039,
      "sourceDate": "2026-01-26"
    },
    {
      "date": "2023-06-01",
      "value": 0.27233076936246103,
      "sourceDate": "2026-01-26"
    },
    {
      "date": "2023-07-01",
      "value": 0.1224556542623878,
      "sourceDate": "2026-01-26"
    },
    {
      "date": "2023-08-01",
      "value": 0.3707226529062968,
      "sourceDate": "2026-01-26"
    },
    {
      "date": "2023-09-01",
      "value": 0.44044533932241503,
      "sourceDate": "2026-01-26"
    },
    {
      "date": "2023-10-01",
      "value": 0.042136442008544606,
      "sourceDate": "2026-01-26"
    },
    {
      "date": "2023-11-01",
      "value": -0.17031063350382292,
      "sourceDate": "2026-01-26"
    },
    {
      "date": "2023-12-01",
      "value": -0.6093211925576214,
      "sourceDate": "2026-01-26"
    },
    {
      "date": "2024-01-01",
      "value": -1.0834024932026565,
      "sourceDate": "2026-01-26"
    },
    {
      "date": "2024-02-01",
      "value": -1.1421513723781196,
      "sourceDate": "2026-01-26"
    },
    {
      "date": "2024-03-01",
      "value": -1.3869443749201515,
      "sourceDate": "2026-01-26"
    },
    {
      "date": "2024-04-01",
      "value": -1.348927015174406,
      "sourceDate": "2026-01-26"
    },
    {
      "date": "2024-05-01",
      "value": -1.2853334510674719,
      "sourceDate": "2026-01-26"
    },
    {
      "date": "2024-06-01",
      "value": -1.6475382795402504,
      "sourceDate": "2026-01-26"
    },
    {
      "date": "2024-07-01",
      "value": -1.7636126817493714,
      "sourceDate": "2026-01-26"
    },
    {
      "date": "2024-08-01",
      "value": -1.900069680610883,
      "sourceDate": "2026-01-26"
    },
    {
      "date": "2024-09-01",
      "value": -1.9799678287662825,
      "sourceDate": "2026-01-26"
    },
    {
      "date": "2024-10-01",
      "value": -2.014733792300649,
      "sourceDate": "2026-01-26"
    },
    {
      "date": "2024-11-01",
      "value": -1.8461337326166283,
      "sourceDate": "2026-01-26"
    },
    {
      "date": "2024-12-01",
      "value": -1.3532248407716163,
      "sourceDate": "2026-01-26"
    },
    {
      "date": "2025-01-01",
      "value": -1.0491972653920323,
      "sourceDate": "2026-01-26"
    },
    {
      "date": "2025-02-01",
      "value": -1.1048162736033262,
      "sourceDate": "2026-01-26"
    },
    {
      "date": "2025-03-01",
      "value": -1.1990916287698106,
      "sourceDate": "2026-01-26"
    },
    {
      "date": "2025-04-01",
      "value": -1.277849806495146,
      "sourceDate": "2026-01-26"
    },
    {
      "date": "2025-05-01",
      "value": -1.1886025577534154,
      "sourceDate": "2026-01-26"
    },
    {
      "date": "2025-06-01",
      "value": -0.7120714118496796,
      "sourceDate": "2026-01-26"
    },
    {
      "date": "2025-07-01",
      "value": -0.6801028495792338,
      "sourceDate": "2026-02-06"
    },
    {
      "date": "2025-08-01",
      "value": -0.9462565733591166,
      "sourceDate": "2026-03-13"
    },
    {
      "date": "2025-09-01",
      "value": -0.6675863372995638,
      "sourceDate": "2026-04-10"
    },
    {
      "date": "2025-10-01",
      "value": -0.21342045970866863,
      "sourceDate": "2026-05-08"
    },
    {
      "date": "2025-11-01",
      "value": -0.015207598526167931,
      "sourceDate": "2026-06-05"
    },
    {
      "date": "2025-12-01",
      "value": -0.26452362990673217,
      "sourceDate": "2026-07-10"
    },
    {
      "date": "2026-01-01",
      "value": -0.4827354212379342,
      "sourceDate": "2026-07-10"
    },
    {
      "date": "2026-02-01",
      "value": -0.7554725389182004,
      "sourceDate": "2026-07-10"
    },
    {
      "date": "2026-03-01",
      "value": -0.4708727783583777,
      "sourceDate": "2026-07-10"
    },
    {
      "date": "2026-04-01",
      "value": -0.4366899258150925,
      "sourceDate": "2026-07-10"
    },
    {
      "date": "2026-05-01",
      "value": 0.007977718974183645,
      "sourceDate": "2026-07-10"
    },
    {
      "date": "2026-06-01",
      "value": -0.16325833081570762,
      "sourceDate": "2026-07-10"
    }
  ],
  "confirmingIndicators": [
    "Employment rate, participation and job composition",
    "Monthly real GDP"
  ],
  "conflictingIndicators": [
    "Population growth and labour-force composition"
  ],
  "evidenceChecks": [],
  "confidenceLevel": "medium",
  "evidenceLabel": "Contextual indicator",
  "calculation": {
    "formula": "YoY percent change in (employment / working-age population)",
    "explanation": "YoY percent change in (employment / working-age population)",
    "example": "Latest observation: -0.16 percent at 2026-06."
  },
  "limitations": [
    "Statistics Canada may revise recent and historical observations.",
    "Cross-country definitions differ."
  ],
  "generatedAt": "2026-07-16T10:23:39+00:00"
}
