{
  "schemaVersion": 1,
  "id": "ontario-shelter-cpi-yoy",
  "field": "ontario_shelter_cpi_yoy",
  "label": "Ontario shelter CPI growth",
  "description": "Ontario housing-cost context",
  "unit": "percent",
  "frequency": "monthly",
  "status": "derived",
  "layer": "Energy affordability and finance",
  "geography": "Ontario",
  "geographyLevel": "provincial",
  "inputType": "domestic",
  "domesticOrExternal": "domestic",
  "directlyComparableAcrossCountries": false,
  "comparisonLimitations": "Definitions, currencies, industrial structure and release timing differ across countries.",
  "core": false,
  "interpretationDirection": "context-dependent",
  "interpretationLabel": "Direction unclear",
  "interpretation": "Ontario housing-cost context",
  "source": "Statistics Canada, StatCan 18-10-0004-01",
  "sourceUrl": "https://www150.statcan.gc.ca/t1/tbl1/en/tv.action?pid=1810000401",
  "sourceIdentifier": "v41691952",
  "seasonalAdjustment": "not seasonally adjusted",
  "nominalOrReal": "price index",
  "startDate": "1979-09-01",
  "endDate": "2026-05-01",
  "latest": {
    "date": "2026-05-01",
    "sourceDate": "2026-06-22",
    "value": 0.15864621893177944,
    "previousValue": 0.15847860538826808,
    "oneYearChange": -1.947185314545541,
    "threeMonthChange": 0.4220814138738205,
    "fourQuarterChange": -1.947185314545541,
    "historicalPercentile": 7.754010695187166,
    "percentileSince2000": 5.205047318611987,
    "distanceFromMedian": -2.8538445966449943,
    "momentum": "rising"
  },
  "referenceRanges": {
    "historicalMedian": 3.012490815576774,
    "p10": 0.3409090909090917,
    "p25": 1.4003294892915852,
    "p75": 4.991087344028511,
    "p90": 7.156308851224091,
    "minimum": -2.1558872305140864,
    "maximum": 15.962441314553978
  },
  "observations": [
    {
      "date": "1979-09-01",
      "value": 5.405405405405395,
      "sourceDate": "2007-06-19"
    },
    {
      "date": "1979-10-01",
      "value": 5.614973262032086,
      "sourceDate": "2007-06-19"
    },
    {
      "date": "1979-11-01",
      "value": 5.8666666666666645,
      "sourceDate": "2007-06-19"
    },
    {
      "date": "1979-12-01",
      "value": 5.8510638297872175,
      "sourceDate": "2007-06-19"
    },
    {
      "date": "1980-01-01",
      "value": 5.804749340369408,
      "sourceDate": "2007-06-19"
    },
    {
      "date": "1980-02-01",
      "value": 6.315789473684208,
      "sourceDate": "2007-06-19"
    },
    {
      "date": "1980-03-01",
      "value": 6.5616797900262425,
      "sourceDate": "2007-06-19"
    },
    {
      "date": "1980-04-01",
      "value": 7.068062827225119,
      "sourceDate": "2007-06-19"
    },
    {
      "date": "1980-05-01",
      "value": 7.59162303664922,
      "sourceDate": "2007-06-19"
    },
    {
      "date": "1980-06-01",
      "value": 7.272727272727275,
      "sourceDate": "2007-06-19"
    },
    {
      "date": "1980-07-01",
      "value": 8.311688311688314,
      "sourceDate": "2007-06-19"
    },
    {
      "date": "1980-08-01",
      "value": 8.290155440414493,
      "sourceDate": "2007-06-19"
    },
    {
      "date": "1980-09-01",
      "value": 7.692307692307687,
      "sourceDate": "2007-06-19"
    },
    {
      "date": "1980-10-01",
      "value": 7.341772151898729,
      "sourceDate": "2007-06-19"
    },
    {
      "date": "1980-11-01",
      "value": 7.304785894206556,
      "sourceDate": "2007-06-19"
    },
    {
      "date": "1980-12-01",
      "value": 8.04020100502514,
      "sourceDate": "2007-06-19"
    },
    {
      "date": "1981-01-01",
      "value": 9.22693266832917,
      "sourceDate": "2007-06-19"
    },
    {
      "date": "1981-02-01",
      "value": 9.158415841584166,
      "sourceDate": "2007-06-19"
    },
    {
      "date": "1981-03-01",
      "value": 9.852216748768484,
      "sourceDate": "2007-06-19"
    },
    {
      "date": "1981-04-01",
      "value": 10.268948655256738,
      "sourceDate": "2007-06-19"
    },
    {
      "date": "1981-05-01",
      "value": 11.19221411192215,
      "sourceDate": "2007-06-19"
    },
    {
      "date": "1981-06-01",
      "value": 12.590799031476996,
      "sourceDate": "2007-06-19"
    },
    {
      "date": "1981-07-01",
      "value": 12.470023980815338,
      "sourceDate": "2007-06-19"
    },
    {
      "date": "1981-08-01",
      "value": 13.157894736842103,
      "sourceDate": "2007-06-19"
    },
    {
      "date": "1981-09-01",
      "value": 13.809523809523805,
      "sourceDate": "2007-06-19"
    },
    {
      "date": "1981-10-01",
      "value": 15.566037735849058,
      "sourceDate": "2007-06-19"
    },
    {
      "date": "1981-11-01",
      "value": 15.962441314553978,
      "sourceDate": "2007-06-19"
    },
    {
      "date": "1981-12-01",
      "value": 15.581395348837223,
      "sourceDate": "2007-06-19"
    },
    {
      "date": "1982-01-01",
      "value": 14.611872146118742,
      "sourceDate": "2007-06-19"
    },
    {
      "date": "1982-02-01",
      "value": 14.739229024943313,
      "sourceDate": "2007-06-19"
    },
    {
      "date": "1982-03-01",
      "value": 15.695067264573993,
      "sourceDate": "2007-06-19"
    },
    {
      "date": "1982-04-01",
      "value": 14.855875831485577,
      "sourceDate": "2007-06-19"
    },
    {
      "date": "1982-05-01",
      "value": 14.004376367614867,
      "sourceDate": "2007-06-19"
    },
    {
      "date": "1982-06-01",
      "value": 12.473118279569896,
      "sourceDate": "2007-06-19"
    },
    {
      "date": "1982-07-01",
      "value": 12.79317697228144,
      "sourceDate": "2007-06-19"
    },
    {
      "date": "1982-08-01",
      "value": 12.262156448202965,
      "sourceDate": "2007-06-19"
    },
    {
      "date": "1982-09-01",
      "value": 12.133891213389125,
      "sourceDate": "2007-06-19"
    },
    {
      "date": "1982-10-01",
      "value": 11.020408163265305,
      "sourceDate": "2007-06-19"
    },
    {
      "date": "1982-11-01",
      "value": 10.526315789473696,
      "sourceDate": "2007-06-19"
    },
    {
      "date": "1982-12-01",
      "value": 10.462776659959761,
      "sourceDate": "2007-06-19"
    },
    {
      "date": "1983-01-01",
      "value": 10.159362549800788,
      "sourceDate": "2007-06-19"
    },
    {
      "date": "1983-02-01",
      "value": 9.486166007905128,
      "sourceDate": "2007-06-19"
    },
    {
      "date": "1983-03-01",
      "value": 8.52713178294573,
      "sourceDate": "2007-06-19"
    },
    {
      "date": "1983-04-01",
      "value": 8.301158301158317,
      "sourceDate": "2007-06-19"
    },
    {
      "date": "1983-05-01",
      "value": 8.061420345489445,
      "sourceDate": "2007-06-19"
    },
    {
      "date": "1983-06-01",
      "value": 7.839388145315485,
      "sourceDate": "2007-06-19"
    },
    {
      "date": "1983-07-01",
      "value": 7.183364839319473,
      "sourceDate": "2007-06-19"
    },
    {
      "date": "1983-08-01",
      "value": 7.156308851224091,
      "sourceDate": "2007-06-19"
    },
    {
      "date": "1983-09-01",
      "value": 6.529850746268662,
      "sourceDate": "2007-06-19"
    },
    {
      "date": "1983-10-01",
      "value": 6.066176470588247,
      "sourceDate": "2007-06-19"
    },
    {
      "date": "1983-11-01",
      "value": 5.860805860805862,
      "sourceDate": "2007-06-19"
    },
    {
      "date": "1983-12-01",
      "value": 5.64663023679417,
      "sourceDate": "2007-06-19"
    },
    {
      "date": "1984-01-01",
      "value": 5.605786618444841,
      "sourceDate": "2007-06-19"
    },
    {
      "date": "1984-02-01",
      "value": 5.776173285198571,
      "sourceDate": "2007-06-19"
    },
    {
      "date": "1984-03-01",
      "value": 5.000000000000004,
      "sourceDate": "2007-06-19"
    },
    {
      "date": "1984-04-01",
      "value": 4.991087344028511,
      "sourceDate": "2007-06-19"
    },
    {
      "date": "1984-05-01",
      "value": 4.618117229129659,
      "sourceDate": "2007-06-19"
    },
    {
      "date": "1984-06-01",
      "value": 4.78723404255319,
      "sourceDate": "2007-06-19"
    },
    {
      "date": "1984-07-01",
      "value": 4.409171075837737,
      "sourceDate": "2007-06-19"
    },
    {
      "date": "1984-08-01",
      "value": 4.393673110720564,
      "sourceDate": "2007-06-19"
    },
    {
      "date": "1984-09-01",
      "value": 4.378283712784592,
      "sourceDate": "2007-06-19"
    },
    {
      "date": "1984-10-01",
      "value": 4.33275563258233,
      "sourceDate": "2007-06-19"
    },
    {
      "date": "1984-11-01",
      "value": 4.671280276816625,
      "sourceDate": "2007-06-19"
    },
    {
      "date": "1984-12-01",
      "value": 4.655172413793118,
      "sourceDate": "2007-06-19"
    },
    {
      "date": "1985-01-01",
      "value": 4.794520547945202,
      "sourceDate": "2007-06-19"
    },
    {
      "date": "1985-02-01",
      "value": 4.778156996587035,
      "sourceDate": "2007-06-19"
    },
    {
      "date": "1985-03-01",
      "value": 4.591836734693877,
      "sourceDate": "2007-06-19"
    },
    {
      "date": "1985-04-01",
      "value": 4.584040747028872,
      "sourceDate": "2007-06-19"
    },
    {
      "date": "1985-05-01",
      "value": 4.923599320882843,
      "sourceDate": "2007-06-19"
    },
    {
      "date": "1985-06-01",
      "value": 4.906937394247035,
      "sourceDate": "2007-06-19"
    },
    {
      "date": "1985-07-01",
      "value": 4.729729729729715,
      "sourceDate": "2007-06-19"
    },
    {
      "date": "1985-08-01",
      "value": 4.7138047138047146,
      "sourceDate": "2007-06-19"
    },
    {
      "date": "1985-09-01",
      "value": 4.530201342281881,
      "sourceDate": "2007-06-19"
    },
    {
      "date": "1985-10-01",
      "value": 4.318936877076407,
      "sourceDate": "2007-06-19"
    },
    {
      "date": "1985-11-01",
      "value": 4.132231404958686,
      "sourceDate": "2007-06-19"
    },
    {
      "date": "1985-12-01",
      "value": 4.1186161449752845,
      "sourceDate": "2007-06-19"
    },
    {
      "date": "1986-01-01",
      "value": 3.7581699346405095,
      "sourceDate": "2007-06-19"
    },
    {
      "date": "1986-02-01",
      "value": 3.9087947882736174,
      "sourceDate": "2007-06-19"
    },
    {
      "date": "1986-03-01",
      "value": 4.065040650406515,
      "sourceDate": "2007-06-19"
    },
    {
      "date": "1986-04-01",
      "value": 3.8961038961038863,
      "sourceDate": "2007-06-19"
    },
    {
      "date": "1986-05-01",
      "value": 3.721682847896446,
      "sourceDate": "2007-06-19"
    },
    {
      "date": "1986-06-01",
      "value": 3.548387096774208,
      "sourceDate": "2007-06-19"
    },
    {
      "date": "1986-07-01",
      "value": 3.8709677419354938,
      "sourceDate": "2007-06-19"
    },
    {
      "date": "1986-08-01",
      "value": 3.858520900321527,
      "sourceDate": "2007-06-19"
    },
    {
      "date": "1986-09-01",
      "value": 4.01284109149278,
      "sourceDate": "2007-06-19"
    },
    {
      "date": "1986-10-01",
      "value": 4.617834394904463,
      "sourceDate": "2007-06-19"
    },
    {
      "date": "1986-11-01",
      "value": 4.603174603174609,
      "sourceDate": "2007-06-19"
    },
    {
      "date": "1986-12-01",
      "value": 4.905063291139222,
      "sourceDate": "2007-06-19"
    },
    {
      "date": "1987-01-01",
      "value": 5.1968503937007915,
      "sourceDate": "2007-06-19"
    },
    {
      "date": "1987-02-01",
      "value": 5.329153605015691,
      "sourceDate": "2007-06-19"
    },
    {
      "date": "1987-03-01",
      "value": 5.781250000000004,
      "sourceDate": "2007-06-19"
    },
    {
      "date": "1987-04-01",
      "value": 7.03125,
      "sourceDate": "2007-06-19"
    },
    {
      "date": "1987-05-01",
      "value": 7.332293291731684,
      "sourceDate": "2007-06-19"
    },
    {
      "date": "1987-06-01",
      "value": 7.3208722741433085,
      "sourceDate": "2007-06-19"
    },
    {
      "date": "1987-07-01",
      "value": 7.608695652173902,
      "sourceDate": "2007-06-19"
    },
    {
      "date": "1987-08-01",
      "value": 7.585139318885448,
      "sourceDate": "2007-06-19"
    },
    {
      "date": "1987-09-01",
      "value": 7.561728395061729,
      "sourceDate": "2007-06-19"
    },
    {
      "date": "1987-10-01",
      "value": 7.001522070015209,
      "sourceDate": "2007-06-19"
    },
    {
      "date": "1987-11-01",
      "value": 7.132018209408186,
      "sourceDate": "2007-06-19"
    },
    {
      "date": "1987-12-01",
      "value": 6.636500754147812,
      "sourceDate": "2007-06-19"
    },
    {
      "date": "1988-01-01",
      "value": 6.437125748502992,
      "sourceDate": "2007-06-19"
    },
    {
      "date": "1988-02-01",
      "value": 5.803571428571419,
      "sourceDate": "2007-06-19"
    },
    {
      "date": "1988-03-01",
      "value": 5.6129985228951185,
      "sourceDate": "2007-06-19"
    },
    {
      "date": "1988-04-01",
      "value": 4.963503649635048,
      "sourceDate": "2007-06-19"
    },
    {
      "date": "1988-05-01",
      "value": 4.941860465116288,
      "sourceDate": "2007-06-19"
    },
    {
      "date": "1988-06-01",
      "value": 5.22496371552974,
      "sourceDate": "2007-06-19"
    },
    {
      "date": "1988-07-01",
      "value": 5.050505050505061,
      "sourceDate": "2007-06-19"
    },
    {
      "date": "1988-08-01",
      "value": 5.4676258992805815,
      "sourceDate": "2007-06-19"
    },
    {
      "date": "1988-09-01",
      "value": 5.7388809182209455,
      "sourceDate": "2007-06-19"
    },
    {
      "date": "1988-10-01",
      "value": 6.258890469416789,
      "sourceDate": "2007-06-19"
    },
    {
      "date": "1988-11-01",
      "value": 6.0906515580736675,
      "sourceDate": "2007-06-19"
    },
    {
      "date": "1988-12-01",
      "value": 6.364922206506374,
      "sourceDate": "2007-06-19"
    },
    {
      "date": "1989-01-01",
      "value": 6.7510548523206815,
      "sourceDate": "2007-06-19"
    },
    {
      "date": "1989-02-01",
      "value": 7.313642756680738,
      "sourceDate": "2007-06-19"
    },
    {
      "date": "1989-03-01",
      "value": 7.4125874125874125,
      "sourceDate": "2007-06-19"
    },
    {
      "date": "1989-04-01",
      "value": 7.6495132127955445,
      "sourceDate": "2007-06-19"
    },
    {
      "date": "1989-05-01",
      "value": 7.479224376731297,
      "sourceDate": "2007-06-19"
    },
    {
      "date": "1989-06-01",
      "value": 7.586206896551717,
      "sourceDate": "2007-06-19"
    },
    {
      "date": "1989-07-01",
      "value": 7.55494505494505,
      "sourceDate": "2007-06-19"
    },
    {
      "date": "1989-08-01",
      "value": 7.230559345156884,
      "sourceDate": "2007-06-19"
    },
    {
      "date": "1989-09-01",
      "value": 6.7842605156037905,
      "sourceDate": "2007-06-19"
    },
    {
      "date": "1989-10-01",
      "value": 7.095046854082998,
      "sourceDate": "2007-06-19"
    },
    {
      "date": "1989-11-01",
      "value": 6.942590120160208,
      "sourceDate": "2007-06-19"
    },
    {
      "date": "1989-12-01",
      "value": 7.047872340425521,
      "sourceDate": "2007-06-19"
    },
    {
      "date": "1990-01-01",
      "value": 7.114624505928835,
      "sourceDate": "2007-06-19"
    },
    {
      "date": "1990-02-01",
      "value": 6.946264744429875,
      "sourceDate": "2007-06-19"
    },
    {
      "date": "1990-03-01",
      "value": 6.640625000000022,
      "sourceDate": "2007-06-19"
    },
    {
      "date": "1990-04-01",
      "value": 6.072351421188604,
      "sourceDate": "2007-06-19"
    },
    {
      "date": "1990-05-01",
      "value": 6.185567010309301,
      "sourceDate": "2007-06-19"
    },
    {
      "date": "1990-06-01",
      "value": 5.641025641025643,
      "sourceDate": "2007-06-19"
    },
    {
      "date": "1990-07-01",
      "value": 4.8531289910600295,
      "sourceDate": "2007-06-19"
    },
    {
      "date": "1990-08-01",
      "value": 4.580152671755733,
      "sourceDate": "2007-06-19"
    },
    {
      "date": "1990-09-01",
      "value": 4.447268106734437,
      "sourceDate": "2007-06-19"
    },
    {
      "date": "1990-10-01",
      "value": 4.125000000000001,
      "sourceDate": "2007-06-19"
    },
    {
      "date": "1990-11-01",
      "value": 4.244694132334592,
      "sourceDate": "2007-06-19"
    },
    {
      "date": "1990-12-01",
      "value": 3.4782608695652195,
      "sourceDate": "2007-06-19"
    },
    {
      "date": "1991-01-01",
      "value": 4.797047970479706,
      "sourceDate": "2007-06-19"
    },
    {
      "date": "1991-02-01",
      "value": 4.4117647058823595,
      "sourceDate": "2007-06-19"
    },
    {
      "date": "1991-03-01",
      "value": 3.296703296703285,
      "sourceDate": "2007-06-19"
    },
    {
      "date": "1991-04-01",
      "value": 3.166869671132777,
      "sourceDate": "2007-06-19"
    },
    {
      "date": "1991-05-01",
      "value": 3.033980582524265,
      "sourceDate": "2007-06-19"
    },
    {
      "date": "1991-06-01",
      "value": 3.398058252427183,
      "sourceDate": "2007-06-19"
    },
    {
      "date": "1991-07-01",
      "value": 4.141291108404399,
      "sourceDate": "2007-06-19"
    },
    {
      "date": "1991-08-01",
      "value": 4.257907542579065,
      "sourceDate": "2007-06-19"
    },
    {
      "date": "1991-09-01",
      "value": 4.257907542579065,
      "sourceDate": "2007-06-19"
    },
    {
      "date": "1991-10-01",
      "value": 3.6014405762304857,
      "sourceDate": "2007-06-19"
    },
    {
      "date": "1991-11-01",
      "value": 3.473053892215572,
      "sourceDate": "2007-06-19"
    },
    {
      "date": "1991-12-01",
      "value": 3.8415366146458574,
      "sourceDate": "2007-06-19"
    },
    {
      "date": "1992-01-01",
      "value": 1.9953051643192499,
      "sourceDate": "2007-06-19"
    },
    {
      "date": "1992-02-01",
      "value": 2.1126760563380254,
      "sourceDate": "2007-06-19"
    },
    {
      "date": "1992-03-01",
      "value": 2.6004728132387633,
      "sourceDate": "2007-06-19"
    },
    {
      "date": "1992-04-01",
      "value": 2.125147579693021,
      "sourceDate": "2007-06-19"
    },
    {
      "date": "1992-05-01",
      "value": 2.1201413427561766,
      "sourceDate": "2007-06-19"
    },
    {
      "date": "1992-06-01",
      "value": 1.5258215962441257,
      "sourceDate": "2007-06-19"
    },
    {
      "date": "1992-07-01",
      "value": 1.2865497076023358,
      "sourceDate": "2007-06-19"
    },
    {
      "date": "1992-08-01",
      "value": 1.0501750291715295,
      "sourceDate": "2007-06-19"
    },
    {
      "date": "1992-09-01",
      "value": 0.933488914819125,
      "sourceDate": "2007-06-19"
    },
    {
      "date": "1992-10-01",
      "value": 0.8111239860950192,
      "sourceDate": "2007-06-19"
    },
    {
      "date": "1992-11-01",
      "value": 0.694444444444442,
      "sourceDate": "2007-06-19"
    },
    {
      "date": "1992-12-01",
      "value": 0.9248554913294793,
      "sourceDate": "2007-06-19"
    },
    {
      "date": "1993-01-01",
      "value": 1.0356731875719172,
      "sourceDate": "2007-06-19"
    },
    {
      "date": "1993-02-01",
      "value": 0.8045977011494232,
      "sourceDate": "2007-06-19"
    },
    {
      "date": "1993-03-01",
      "value": 0.9216589861751112,
      "sourceDate": "2007-06-19"
    },
    {
      "date": "1993-04-01",
      "value": 1.0404624277456698,
      "sourceDate": "2007-06-19"
    },
    {
      "date": "1993-05-01",
      "value": 0.5767012687427853,
      "sourceDate": "2007-06-19"
    },
    {
      "date": "1993-06-01",
      "value": 0.9248554913294793,
      "sourceDate": "2007-06-19"
    },
    {
      "date": "1993-07-01",
      "value": 0.9237875288683695,
      "sourceDate": "2007-06-19"
    },
    {
      "date": "1993-08-01",
      "value": 0.6928406466512715,
      "sourceDate": "2007-06-19"
    },
    {
      "date": "1993-09-01",
      "value": 1.0404624277456698,
      "sourceDate": "2007-06-19"
    },
    {
      "date": "1993-10-01",
      "value": 1.1494252873563315,
      "sourceDate": "2007-06-19"
    },
    {
      "date": "1993-11-01",
      "value": 1.0344827586207028,
      "sourceDate": "2007-06-19"
    },
    {
      "date": "1993-12-01",
      "value": 0.8018327605956443,
      "sourceDate": "2007-06-19"
    },
    {
      "date": "1994-01-01",
      "value": 0.0,
      "sourceDate": "2007-06-19"
    },
    {
      "date": "1994-02-01",
      "value": 0.11402508551880963,
      "sourceDate": "2007-06-19"
    },
    {
      "date": "1994-03-01",
      "value": 0.11415525114155667,
      "sourceDate": "2007-06-19"
    },
    {
      "date": "1994-04-01",
      "value": -0.22883295194507935,
      "sourceDate": "2007-06-19"
    },
    {
      "date": "1994-05-01",
      "value": 0.0,
      "sourceDate": "2007-06-19"
    },
    {
      "date": "1994-06-01",
      "value": 0.11454753722794919,
      "sourceDate": "2007-06-19"
    },
    {
      "date": "1994-07-01",
      "value": 0.0,
      "sourceDate": "2007-06-19"
    },
    {
      "date": "1994-08-01",
      "value": 0.5733944954128489,
      "sourceDate": "2007-06-19"
    },
    {
      "date": "1994-09-01",
      "value": 0.4576659038901587,
      "sourceDate": "2007-06-19"
    },
    {
      "date": "1994-10-01",
      "value": -0.1136363636363602,
      "sourceDate": "2007-06-19"
    },
    {
      "date": "1994-11-01",
      "value": 0.0,
      "sourceDate": "2007-06-19"
    },
    {
      "date": "1994-12-01",
      "value": 0.3409090909090917,
      "sourceDate": "2007-06-19"
    },
    {
      "date": "1995-01-01",
      "value": 0.7972665148063829,
      "sourceDate": "2007-06-19"
    },
    {
      "date": "1995-02-01",
      "value": 1.025056947608216,
      "sourceDate": "2007-06-19"
    },
    {
      "date": "1995-03-01",
      "value": 1.2542759407069504,
      "sourceDate": "2007-06-19"
    },
    {
      "date": "1995-04-01",
      "value": 1.4908256880733939,
      "sourceDate": "2007-06-19"
    },
    {
      "date": "1995-05-01",
      "value": 1.83486238532109,
      "sourceDate": "2007-06-19"
    },
    {
      "date": "1995-06-01",
      "value": 1.6018306636155444,
      "sourceDate": "2007-06-19"
    },
    {
      "date": "1995-07-01",
      "value": 1.4874141876430214,
      "sourceDate": "2007-06-19"
    },
    {
      "date": "1995-08-01",
      "value": 1.1402508551881407,
      "sourceDate": "2007-06-19"
    },
    {
      "date": "1995-09-01",
      "value": 1.025056947608216,
      "sourceDate": "2007-06-19"
    },
    {
      "date": "1995-10-01",
      "value": 0.682593856655278,
      "sourceDate": "2007-06-19"
    },
    {
      "date": "1995-11-01",
      "value": 0.9101251422070522,
      "sourceDate": "2007-06-19"
    },
    {
      "date": "1995-12-01",
      "value": 0.5662514156285381,
      "sourceDate": "2007-06-19"
    },
    {
      "date": "1996-01-01",
      "value": 0.3389830508474523,
      "sourceDate": "2007-06-19"
    },
    {
      "date": "1996-02-01",
      "value": 0.11273957158961512,
      "sourceDate": "2007-06-19"
    },
    {
      "date": "1996-03-01",
      "value": -0.11261261261260591,
      "sourceDate": "2007-06-19"
    },
    {
      "date": "1996-04-01",
      "value": 0.11299435028246929,
      "sourceDate": "2007-06-19"
    },
    {
      "date": "1996-05-01",
      "value": -0.11261261261260591,
      "sourceDate": "2007-06-19"
    },
    {
      "date": "1996-06-01",
      "value": -0.33783783783783994,
      "sourceDate": "2007-06-19"
    },
    {
      "date": "1996-07-01",
      "value": -0.22547914317926354,
      "sourceDate": "2007-06-19"
    },
    {
      "date": "1996-08-01",
      "value": -0.33821871476887866,
      "sourceDate": "2007-06-19"
    },
    {
      "date": "1996-09-01",
      "value": -0.22547914317926354,
      "sourceDate": "2007-06-19"
    },
    {
      "date": "1996-10-01",
      "value": 0.7909604519773961,
      "sourceDate": "2007-06-19"
    },
    {
      "date": "1996-11-01",
      "value": -0.22547914317926354,
      "sourceDate": "2007-06-19"
    },
    {
      "date": "1996-12-01",
      "value": -0.11261261261260591,
      "sourceDate": "2007-06-19"
    },
    {
      "date": "1997-01-01",
      "value": -0.11261261261260591,
      "sourceDate": "2007-06-19"
    },
    {
      "date": "1997-02-01",
      "value": -0.11261261261260591,
      "sourceDate": "2007-06-19"
    },
    {
      "date": "1997-03-01",
      "value": 0.33821871476888976,
      "sourceDate": "2007-06-19"
    },
    {
      "date": "1997-04-01",
      "value": 0.3386004514672747,
      "sourceDate": "2007-06-19"
    },
    {
      "date": "1997-05-01",
      "value": 0.11273957158961512,
      "sourceDate": "2007-06-19"
    },
    {
      "date": "1997-06-01",
      "value": 0.3389830508474523,
      "sourceDate": "2007-06-19"
    },
    {
      "date": "1997-07-01",
      "value": 0.4519774011299438,
      "sourceDate": "2007-06-19"
    },
    {
      "date": "1997-08-01",
      "value": 0.2262443438913797,
      "sourceDate": "2007-06-19"
    },
    {
      "date": "1997-09-01",
      "value": 0.11299435028246929,
      "sourceDate": "2007-06-19"
    },
    {
      "date": "1997-10-01",
      "value": -0.33632286995515237,
      "sourceDate": "2007-06-19"
    },
    {
      "date": "1997-11-01",
      "value": 0.11299435028246929,
      "sourceDate": "2007-06-19"
    },
    {
      "date": "1997-12-01",
      "value": 0.22547914317925244,
      "sourceDate": "2007-06-19"
    },
    {
      "date": "1998-01-01",
      "value": 0.22547914317925244,
      "sourceDate": "2007-06-19"
    },
    {
      "date": "1998-02-01",
      "value": 0.33821871476888976,
      "sourceDate": "2007-06-19"
    },
    {
      "date": "1998-03-01",
      "value": 0.11235955056179137,
      "sourceDate": "2007-06-19"
    },
    {
      "date": "1998-04-01",
      "value": 0.0,
      "sourceDate": "2007-06-19"
    },
    {
      "date": "1998-05-01",
      "value": 0.33783783783782884,
      "sourceDate": "2007-06-19"
    },
    {
      "date": "1998-06-01",
      "value": 0.22522522522523403,
      "sourceDate": "2007-06-19"
    },
    {
      "date": "1998-07-01",
      "value": 0.5624296962879693,
      "sourceDate": "2007-06-19"
    },
    {
      "date": "1998-08-01",
      "value": 0.7900677200902928,
      "sourceDate": "2007-06-19"
    },
    {
      "date": "1998-09-01",
      "value": 1.0158013544018019,
      "sourceDate": "2007-06-19"
    },
    {
      "date": "1998-10-01",
      "value": 1.3498312710910954,
      "sourceDate": "2007-06-19"
    },
    {
      "date": "1998-11-01",
      "value": 1.5801354401805856,
      "sourceDate": "2007-06-19"
    },
    {
      "date": "1998-12-01",
      "value": 1.5748031496062964,
      "sourceDate": "2007-06-19"
    },
    {
      "date": "1999-01-01",
      "value": 1.6872890888638858,
      "sourceDate": "2007-06-19"
    },
    {
      "date": "1999-02-01",
      "value": 1.4606741573033766,
      "sourceDate": "2007-06-19"
    },
    {
      "date": "1999-03-01",
      "value": 1.3468013468013407,
      "sourceDate": "2007-06-19"
    },
    {
      "date": "1999-04-01",
      "value": 1.7997750281214753,
      "sourceDate": "2007-06-19"
    },
    {
      "date": "1999-05-01",
      "value": 1.4590347923681302,
      "sourceDate": "2007-06-19"
    },
    {
      "date": "1999-06-01",
      "value": 1.6853932584269593,
      "sourceDate": "2007-06-19"
    },
    {
      "date": "1999-07-01",
      "value": 1.342281879194629,
      "sourceDate": "2007-06-19"
    },
    {
      "date": "1999-08-01",
      "value": 1.5677491601343796,
      "sourceDate": "2007-06-19"
    },
    {
      "date": "1999-09-01",
      "value": 1.787709497206702,
      "sourceDate": "2007-06-19"
    },
    {
      "date": "1999-10-01",
      "value": 1.1098779134295134,
      "sourceDate": "2007-06-19"
    },
    {
      "date": "1999-11-01",
      "value": 1.333333333333342,
      "sourceDate": "2007-06-19"
    },
    {
      "date": "1999-12-01",
      "value": 1.661129568106312,
      "sourceDate": "2007-06-19"
    },
    {
      "date": "2000-01-01",
      "value": 1.880530973451311,
      "sourceDate": "2007-06-19"
    },
    {
      "date": "2000-02-01",
      "value": 2.7685492801771794,
      "sourceDate": "2007-06-19"
    },
    {
      "date": "2000-03-01",
      "value": 2.879291251384286,
      "sourceDate": "2007-06-19"
    },
    {
      "date": "2000-04-01",
      "value": 2.541436464088398,
      "sourceDate": "2007-06-19"
    },
    {
      "date": "2000-05-01",
      "value": 2.765486725663724,
      "sourceDate": "2007-06-19"
    },
    {
      "date": "2000-06-01",
      "value": 3.2044198895027742,
      "sourceDate": "2007-06-19"
    },
    {
      "date": "2000-07-01",
      "value": 3.4216335540838916,
      "sourceDate": "2007-06-19"
    },
    {
      "date": "2000-08-01",
      "value": 3.528114663726578,
      "sourceDate": "2007-06-19"
    },
    {
      "date": "2000-09-01",
      "value": 3.4028540065861757,
      "sourceDate": "2007-06-19"
    },
    {
      "date": "2000-10-01",
      "value": 4.829857299670692,
      "sourceDate": "2007-06-19"
    },
    {
      "date": "2000-11-01",
      "value": 5.592105263157898,
      "sourceDate": "2007-06-19"
    },
    {
      "date": "2000-12-01",
      "value": 5.119825708060999,
      "sourceDate": "2007-06-19"
    },
    {
      "date": "2001-01-01",
      "value": 5.646036916395225,
      "sourceDate": "2007-06-19"
    },
    {
      "date": "2001-02-01",
      "value": 4.956896551724155,
      "sourceDate": "2007-06-19"
    },
    {
      "date": "2001-03-01",
      "value": 6.458557588805158,
      "sourceDate": "2007-06-19"
    },
    {
      "date": "2001-04-01",
      "value": 6.465517241379315,
      "sourceDate": "2007-06-19"
    },
    {
      "date": "2001-05-01",
      "value": 6.566200215285245,
      "sourceDate": "2007-06-19"
    },
    {
      "date": "2001-06-01",
      "value": 6.638115631691632,
      "sourceDate": "2007-06-19"
    },
    {
      "date": "2001-07-01",
      "value": 6.510138740661686,
      "sourceDate": "2007-06-19"
    },
    {
      "date": "2001-08-01",
      "value": 6.176783812566566,
      "sourceDate": "2007-06-19"
    },
    {
      "date": "2001-09-01",
      "value": 5.307855626326963,
      "sourceDate": "2007-06-19"
    },
    {
      "date": "2001-10-01",
      "value": 4.607329842931951,
      "sourceDate": "2007-06-19"
    },
    {
      "date": "2001-11-01",
      "value": 3.1152647975077885,
      "sourceDate": "2007-06-19"
    },
    {
      "date": "2001-12-01",
      "value": 3.1088082901554515,
      "sourceDate": "2007-06-19"
    },
    {
      "date": "2002-01-01",
      "value": 2.261048304213764,
      "sourceDate": "2007-06-19"
    },
    {
      "date": "2002-02-01",
      "value": 2.258726899383978,
      "sourceDate": "2007-06-19"
    },
    {
      "date": "2002-03-01",
      "value": 1.5166835187057526,
      "sourceDate": "2007-06-19"
    },
    {
      "date": "2002-04-01",
      "value": 0.30364372469635637,
      "sourceDate": "2007-06-19"
    },
    {
      "date": "2002-05-01",
      "value": 0.3030303030302939,
      "sourceDate": "2007-06-19"
    },
    {
      "date": "2002-06-01",
      "value": -0.6024096385542133,
      "sourceDate": "2007-06-19"
    },
    {
      "date": "2002-07-01",
      "value": -0.4008016032064021,
      "sourceDate": "2007-06-19"
    },
    {
      "date": "2002-08-01",
      "value": 1.8054162487462388,
      "sourceDate": "2007-06-19"
    },
    {
      "date": "2002-09-01",
      "value": 1.7137096774193505,
      "sourceDate": "2007-06-19"
    },
    {
      "date": "2002-10-01",
      "value": 2.0020020020020013,
      "sourceDate": "2007-06-19"
    },
    {
      "date": "2002-11-01",
      "value": 2.316213494461228,
      "sourceDate": "2007-06-19"
    },
    {
      "date": "2002-12-01",
      "value": -1.8090452261306456,
      "sourceDate": "2007-06-19"
    },
    {
      "date": "2003-01-01",
      "value": 2.01005025125629,
      "sourceDate": "2007-06-19"
    },
    {
      "date": "2003-02-01",
      "value": 2.208835341365467,
      "sourceDate": "2007-06-19"
    },
    {
      "date": "2003-03-01",
      "value": 1.7928286852589626,
      "sourceDate": "2007-06-19"
    },
    {
      "date": "2003-04-01",
      "value": 1.31180625630678,
      "sourceDate": "2007-06-19"
    },
    {
      "date": "2003-05-01",
      "value": 3.0211480362537735,
      "sourceDate": "2007-06-19"
    },
    {
      "date": "2003-06-01",
      "value": 4.141414141414135,
      "sourceDate": "2007-06-19"
    },
    {
      "date": "2003-07-01",
      "value": 3.621730382293764,
      "sourceDate": "2007-06-19"
    },
    {
      "date": "2003-08-01",
      "value": 1.9704433497536922,
      "sourceDate": "2007-06-19"
    },
    {
      "date": "2003-09-01",
      "value": 2.6759167492566682,
      "sourceDate": "2007-06-19"
    },
    {
      "date": "2003-10-01",
      "value": 1.7664376840039298,
      "sourceDate": "2007-06-19"
    },
    {
      "date": "2003-11-01",
      "value": 2.1653543307086576,
      "sourceDate": "2007-06-19"
    },
    {
      "date": "2003-12-01",
      "value": 6.857727737973396,
      "sourceDate": "2007-06-19"
    },
    {
      "date": "2004-01-01",
      "value": 2.364532019704435,
      "sourceDate": "2007-06-19"
    },
    {
      "date": "2004-02-01",
      "value": 2.259332023575644,
      "sourceDate": "2007-06-19"
    },
    {
      "date": "2004-03-01",
      "value": 2.1526418786692814,
      "sourceDate": "2007-06-19"
    },
    {
      "date": "2004-04-01",
      "value": 4.581673306772904,
      "sourceDate": "2007-06-19"
    },
    {
      "date": "2004-05-01",
      "value": 2.834799608993155,
      "sourceDate": "2007-06-19"
    },
    {
      "date": "2004-06-01",
      "value": 2.13385063045588,
      "sourceDate": "2007-06-19"
    },
    {
      "date": "2004-07-01",
      "value": 2.9126213592232997,
      "sourceDate": "2007-06-19"
    },
    {
      "date": "2004-08-01",
      "value": 2.512077294685988,
      "sourceDate": "2007-06-19"
    },
    {
      "date": "2004-09-01",
      "value": 2.6061776061776065,
      "sourceDate": "2007-06-19"
    },
    {
      "date": "2004-10-01",
      "value": 2.892960462873684,
      "sourceDate": "2007-06-19"
    },
    {
      "date": "2004-11-01",
      "value": 3.0828516377649384,
      "sourceDate": "2007-06-19"
    },
    {
      "date": "2004-12-01",
      "value": 2.5862068965517127,
      "sourceDate": "2007-06-19"
    },
    {
      "date": "2005-01-01",
      "value": 3.368623676612126,
      "sourceDate": "2007-06-19"
    },
    {
      "date": "2005-02-01",
      "value": 3.6503362151777186,
      "sourceDate": "2007-06-19"
    },
    {
      "date": "2005-03-01",
      "value": 3.6398467432950055,
      "sourceDate": "2007-06-19"
    },
    {
      "date": "2005-04-01",
      "value": 3.0476190476190546,
      "sourceDate": "2007-06-19"
    },
    {
      "date": "2005-05-01",
      "value": 3.2319391634980876,
      "sourceDate": "2007-06-19"
    },
    {
      "date": "2005-06-01",
      "value": 3.3238366571699984,
      "sourceDate": "2007-06-19"
    },
    {
      "date": "2005-07-01",
      "value": 3.018867924528301,
      "sourceDate": "2007-06-19"
    },
    {
      "date": "2005-08-01",
      "value": 3.016022620169645,
      "sourceDate": "2007-06-19"
    },
    {
      "date": "2005-09-01",
      "value": 3.1044214487299993,
      "sourceDate": "2007-06-19"
    },
    {
      "date": "2005-10-01",
      "value": 3.373945641986875,
      "sourceDate": "2007-06-19"
    },
    {
      "date": "2005-11-01",
      "value": 3.17757009345796,
      "sourceDate": "2007-06-19"
    },
    {
      "date": "2005-12-01",
      "value": 2.8944911297852594,
      "sourceDate": "2007-06-19"
    },
    {
      "date": "2006-01-01",
      "value": 4.003724394785846,
      "sourceDate": "2007-06-19"
    },
    {
      "date": "2006-02-01",
      "value": 3.7998146431881263,
      "sourceDate": "2007-06-19"
    },
    {
      "date": "2006-03-01",
      "value": 3.6968576709796697,
      "sourceDate": "2007-06-19"
    },
    {
      "date": "2006-04-01",
      "value": 3.2347504621072165,
      "sourceDate": "2007-06-19"
    },
    {
      "date": "2006-05-01",
      "value": 4.05156537753224,
      "sourceDate": "2007-06-19"
    },
    {
      "date": "2006-06-01",
      "value": 3.768382352941191,
      "sourceDate": "2007-06-19"
    },
    {
      "date": "2006-07-01",
      "value": 3.0219780219780112,
      "sourceDate": "2007-06-19"
    },
    {
      "date": "2006-08-01",
      "value": 3.1107044830741115,
      "sourceDate": "2007-06-19"
    },
    {
      "date": "2006-09-01",
      "value": 2.9197080291970767,
      "sourceDate": "2007-06-19"
    },
    {
      "date": "2006-10-01",
      "value": 2.447869446962825,
      "sourceDate": "2007-06-19"
    },
    {
      "date": "2006-11-01",
      "value": 1.8115942028985588,
      "sourceDate": "2007-06-19"
    },
    {
      "date": "2006-12-01",
      "value": 2.4500907441016295,
      "sourceDate": "2007-06-19"
    },
    {
      "date": "2007-01-01",
      "value": 1.07430617726052,
      "sourceDate": "2007-06-19"
    },
    {
      "date": "2007-02-01",
      "value": 0.8035714285714368,
      "sourceDate": "2007-06-19"
    },
    {
      "date": "2007-03-01",
      "value": 0.9803921568627416,
      "sourceDate": "2007-06-19"
    },
    {
      "date": "2007-04-01",
      "value": 2.2381378692927445,
      "sourceDate": "2007-06-19"
    },
    {
      "date": "2007-05-01",
      "value": 1.0619469026548645,
      "sourceDate": "2007-06-19"
    },
    {
      "date": "2007-06-01",
      "value": 1.3286093888396744,
      "sourceDate": "2007-07-18"
    },
    {
      "date": "2007-07-01",
      "value": 1.6888888888888953,
      "sourceDate": "2007-08-21"
    },
    {
      "date": "2007-08-01",
      "value": 1.7746228926353247,
      "sourceDate": "2007-09-19"
    },
    {
      "date": "2007-09-01",
      "value": 1.9503546099290725,
      "sourceDate": "2007-10-19"
    },
    {
      "date": "2007-10-01",
      "value": 2.6548672566371723,
      "sourceDate": "2007-11-20"
    },
    {
      "date": "2007-11-01",
      "value": 2.758007117437722,
      "sourceDate": "2007-12-18"
    },
    {
      "date": "2007-12-01",
      "value": 2.5686448184233823,
      "sourceDate": "2008-01-25"
    },
    {
      "date": "2008-01-01",
      "value": 2.391496899911405,
      "sourceDate": "2008-02-19"
    },
    {
      "date": "2008-02-01",
      "value": 2.657218777679371,
      "sourceDate": "2008-03-18"
    },
    {
      "date": "2008-03-01",
      "value": 2.6478375992939007,
      "sourceDate": "2008-04-17"
    },
    {
      "date": "2008-04-01",
      "value": 2.539404553415059,
      "sourceDate": "2008-05-21"
    },
    {
      "date": "2008-05-01",
      "value": 2.889667250437822,
      "sourceDate": "2008-06-19"
    },
    {
      "date": "2008-06-01",
      "value": 2.7972027972027913,
      "sourceDate": "2008-07-23"
    },
    {
      "date": "2008-07-01",
      "value": 4.807692307692313,
      "sourceDate": "2008-08-21"
    },
    {
      "date": "2008-08-01",
      "value": 4.620749782040101,
      "sourceDate": "2008-09-23"
    },
    {
      "date": "2008-09-01",
      "value": 4.17391304347825,
      "sourceDate": "2008-10-24"
    },
    {
      "date": "2008-10-01",
      "value": 3.534482758620694,
      "sourceDate": "2008-11-21"
    },
    {
      "date": "2008-11-01",
      "value": 4.415584415584406,
      "sourceDate": "2008-12-19"
    },
    {
      "date": "2008-12-01",
      "value": 4.145077720207246,
      "sourceDate": "2009-01-23"
    },
    {
      "date": "2009-01-01",
      "value": 4.065743944636679,
      "sourceDate": "2009-02-20"
    },
    {
      "date": "2009-02-01",
      "value": 3.796376186367545,
      "sourceDate": "2009-03-19"
    },
    {
      "date": "2009-03-01",
      "value": 3.353396388650043,
      "sourceDate": "2009-04-17"
    },
    {
      "date": "2009-04-01",
      "value": 0.853970964987183,
      "sourceDate": "2009-05-20"
    },
    {
      "date": "2009-05-01",
      "value": 0.6808510638297793,
      "sourceDate": "2009-06-18"
    },
    {
      "date": "2009-06-01",
      "value": 0.5952380952380931,
      "sourceDate": "2009-07-17"
    },
    {
      "date": "2009-07-01",
      "value": -1.7514595496246899,
      "sourceDate": "2009-08-19"
    },
    {
      "date": "2009-08-01",
      "value": -1.9166666666666665,
      "sourceDate": "2009-09-17"
    },
    {
      "date": "2009-09-01",
      "value": -1.7529215358931483,
      "sourceDate": "2009-10-16"
    },
    {
      "date": "2009-10-01",
      "value": -1.582014987510405,
      "sourceDate": "2009-11-18"
    },
    {
      "date": "2009-11-01",
      "value": -2.1558872305140864,
      "sourceDate": "2009-12-17"
    },
    {
      "date": "2009-12-01",
      "value": -1.990049751243772,
      "sourceDate": "2010-01-20"
    },
    {
      "date": "2010-01-01",
      "value": -1.413133832086455,
      "sourceDate": "2010-02-18"
    },
    {
      "date": "2010-02-01",
      "value": -1.413133832086455,
      "sourceDate": "2010-03-19"
    },
    {
      "date": "2010-03-01",
      "value": -1.1647254575707255,
      "sourceDate": "2010-04-23"
    },
    {
      "date": "2010-04-01",
      "value": 1.6088060965283812,
      "sourceDate": "2010-05-21"
    },
    {
      "date": "2010-05-01",
      "value": 2.6204564666103103,
      "sourceDate": "2010-06-22"
    },
    {
      "date": "2010-06-01",
      "value": 2.6204564666103103,
      "sourceDate": "2010-07-23"
    },
    {
      "date": "2010-07-01",
      "value": 4.329371816638372,
      "sourceDate": "2010-08-20"
    },
    {
      "date": "2010-08-01",
      "value": 4.078164825828368,
      "sourceDate": "2010-09-21"
    },
    {
      "date": "2010-09-01",
      "value": 4.078164825828368,
      "sourceDate": "2010-10-22"
    },
    {
      "date": "2010-10-01",
      "value": 4.230118443316422,
      "sourceDate": "2010-11-23"
    },
    {
      "date": "2010-11-01",
      "value": 4.067796610169494,
      "sourceDate": "2010-12-21"
    },
    {
      "date": "2010-12-01",
      "value": 4.060913705583746,
      "sourceDate": "2011-01-25"
    },
    {
      "date": "2011-01-01",
      "value": 3.204047217537953,
      "sourceDate": "2011-02-18"
    },
    {
      "date": "2011-02-01",
      "value": 2.4451939291737057,
      "sourceDate": "2011-03-18"
    },
    {
      "date": "2011-03-01",
      "value": 2.6936026936027035,
      "sourceDate": "2011-04-19"
    },
    {
      "date": "2011-04-01",
      "value": 1.8333333333333313,
      "sourceDate": "2011-05-20"
    },
    {
      "date": "2011-05-01",
      "value": 1.317957166392092,
      "sourceDate": "2011-06-29"
    },
    {
      "date": "2011-06-01",
      "value": 1.4003294892915852,
      "sourceDate": "2011-07-22"
    },
    {
      "date": "2011-07-01",
      "value": 0.4882017900732283,
      "sourceDate": "2011-08-19"
    },
    {
      "date": "2011-08-01",
      "value": 0.897959183673458,
      "sourceDate": "2011-09-21"
    },
    {
      "date": "2011-09-01",
      "value": 0.897959183673458,
      "sourceDate": "2011-10-21"
    },
    {
      "date": "2011-10-01",
      "value": 0.48701298701299134,
      "sourceDate": "2011-11-18"
    },
    {
      "date": "2011-11-01",
      "value": 0.8957654723127151,
      "sourceDate": "2011-12-20"
    },
    {
      "date": "2011-12-01",
      "value": 0.8943089430894169,
      "sourceDate": "2012-01-20"
    },
    {
      "date": "2012-01-01",
      "value": 1.552287581699341,
      "sourceDate": "2012-02-17"
    },
    {
      "date": "2012-02-01",
      "value": 2.304526748971192,
      "sourceDate": "2012-03-23"
    },
    {
      "date": "2012-03-01",
      "value": 1.967213114754096,
      "sourceDate": "2012-04-20"
    },
    {
      "date": "2012-04-01",
      "value": 1.8003273322422242,
      "sourceDate": "2012-05-18"
    },
    {
      "date": "2012-05-01",
      "value": 1.788617886178856,
      "sourceDate": "2012-06-22"
    },
    {
      "date": "2012-06-01",
      "value": 1.7871649065800188,
      "sourceDate": "2012-07-20"
    },
    {
      "date": "2012-07-01",
      "value": 1.538461538461533,
      "sourceDate": "2012-08-17"
    },
    {
      "date": "2012-08-01",
      "value": 1.4563106796116498,
      "sourceDate": "2012-09-21"
    },
    {
      "date": "2012-09-01",
      "value": 1.2944983818770295,
      "sourceDate": "2012-10-19"
    },
    {
      "date": "2012-10-01",
      "value": 1.3731825525040486,
      "sourceDate": "2012-11-23"
    },
    {
      "date": "2012-11-01",
      "value": 1.2106537530266248,
      "sourceDate": "2012-12-21"
    },
    {
      "date": "2012-12-01",
      "value": 1.0475423045930743,
      "sourceDate": "2013-01-25"
    },
    {
      "date": "2013-01-01",
      "value": 1.2872083668543866,
      "sourceDate": "2021-07-28"
    },
    {
      "date": "2013-02-01",
      "value": 1.4481094127111849,
      "sourceDate": "2021-07-28"
    },
    {
      "date": "2013-03-01",
      "value": 1.3665594855305274,
      "sourceDate": "2021-07-28"
    },
    {
      "date": "2013-04-01",
      "value": 1.3665594855305274,
      "sourceDate": "2021-07-28"
    },
    {
      "date": "2013-05-01",
      "value": 0.9584664536741228,
      "sourceDate": "2021-07-28"
    },
    {
      "date": "2013-06-01",
      "value": 1.037509976057449,
      "sourceDate": "2021-07-28"
    },
    {
      "date": "2013-07-01",
      "value": 1.3556618819776656,
      "sourceDate": "2021-07-28"
    },
    {
      "date": "2013-08-01",
      "value": 1.4354066985645897,
      "sourceDate": "2021-07-28"
    },
    {
      "date": "2013-09-01",
      "value": 1.757188498402562,
      "sourceDate": "2021-07-28"
    },
    {
      "date": "2013-10-01",
      "value": 1.5139442231075773,
      "sourceDate": "2021-07-28"
    },
    {
      "date": "2013-11-01",
      "value": 2.1531100478468845,
      "sourceDate": "2021-07-28"
    },
    {
      "date": "2013-12-01",
      "value": 2.3125996810207328,
      "sourceDate": "2021-07-28"
    },
    {
      "date": "2014-01-01",
      "value": 2.30341540905481,
      "sourceDate": "2021-07-28"
    },
    {
      "date": "2014-02-01",
      "value": 2.2204599524187296,
      "sourceDate": "2021-07-28"
    },
    {
      "date": "2014-03-01",
      "value": 2.3790642347343294,
      "sourceDate": "2021-07-28"
    },
    {
      "date": "2014-04-01",
      "value": 4.599524187153059,
      "sourceDate": "2021-07-28"
    },
    {
      "date": "2014-05-01",
      "value": 4.746835443037978,
      "sourceDate": "2021-07-28"
    },
    {
      "date": "2014-06-01",
      "value": 4.502369668246464,
      "sourceDate": "2021-07-28"
    },
    {
      "date": "2014-07-01",
      "value": 3.933910306845001,
      "sourceDate": "2021-07-28"
    },
    {
      "date": "2014-08-01",
      "value": 3.8522012578616316,
      "sourceDate": "2021-07-28"
    },
    {
      "date": "2014-09-01",
      "value": 3.689167974882257,
      "sourceDate": "2021-07-28"
    },
    {
      "date": "2014-10-01",
      "value": 3.8461538461538547,
      "sourceDate": "2021-07-28"
    },
    {
      "date": "2014-11-01",
      "value": 3.512880562060894,
      "sourceDate": "2021-07-28"
    },
    {
      "date": "2014-12-01",
      "value": 3.585346843335935,
      "sourceDate": "2021-07-28"
    },
    {
      "date": "2015-01-01",
      "value": 3.5714285714285587,
      "sourceDate": "2021-07-28"
    },
    {
      "date": "2015-02-01",
      "value": 3.5686578743211683,
      "sourceDate": "2021-07-28"
    },
    {
      "date": "2015-03-01",
      "value": 3.640588690937263,
      "sourceDate": "2021-07-28"
    },
    {
      "date": "2015-04-01",
      "value": 1.2130401819560266,
      "sourceDate": "2021-07-28"
    },
    {
      "date": "2015-05-01",
      "value": 1.283987915407847,
      "sourceDate": "2021-07-28"
    },
    {
      "date": "2015-06-01",
      "value": 1.5873015873015817,
      "sourceDate": "2021-07-28"
    },
    {
      "date": "2015-07-01",
      "value": 2.1196063588190928,
      "sourceDate": "2021-07-28"
    },
    {
      "date": "2015-08-01",
      "value": 2.195306585919754,
      "sourceDate": "2021-07-28"
    },
    {
      "date": "2015-09-01",
      "value": 2.2710068130204375,
      "sourceDate": "2021-07-28"
    },
    {
      "date": "2015-10-01",
      "value": 2.0408163265306145,
      "sourceDate": "2021-07-28"
    },
    {
      "date": "2015-11-01",
      "value": 2.0361990950226394,
      "sourceDate": "2021-07-28"
    },
    {
      "date": "2015-12-01",
      "value": 1.9563581640331007,
      "sourceDate": "2021-07-28"
    },
    {
      "date": "2016-01-01",
      "value": 2.0239880059969906,
      "sourceDate": "2021-07-28"
    },
    {
      "date": "2016-02-01",
      "value": 2.0224719101123556,
      "sourceDate": "2021-07-28"
    },
    {
      "date": "2016-03-01",
      "value": 2.0179372197309364,
      "sourceDate": "2021-07-28"
    },
    {
      "date": "2016-04-01",
      "value": 2.5468164794007597,
      "sourceDate": "2021-07-28"
    },
    {
      "date": "2016-05-01",
      "value": 2.5354213273676374,
      "sourceDate": "2021-07-28"
    },
    {
      "date": "2016-06-01",
      "value": 2.678571428571419,
      "sourceDate": "2021-07-28"
    },
    {
      "date": "2016-07-01",
      "value": 2.6686434395848835,
      "sourceDate": "2021-07-28"
    },
    {
      "date": "2016-08-01",
      "value": 2.7407407407407325,
      "sourceDate": "2021-07-28"
    },
    {
      "date": "2016-09-01",
      "value": 2.812731310140637,
      "sourceDate": "2021-07-28"
    },
    {
      "date": "2016-10-01",
      "value": 3.3333333333333437,
      "sourceDate": "2021-07-28"
    },
    {
      "date": "2016-11-01",
      "value": 3.3998521803399795,
      "sourceDate": "2021-07-28"
    },
    {
      "date": "2016-12-01",
      "value": 3.394833948339482,
      "sourceDate": "2021-07-28"
    },
    {
      "date": "2017-01-01",
      "value": 3.012490815576774,
      "sourceDate": "2021-07-28"
    },
    {
      "date": "2017-02-01",
      "value": 2.936857562408224,
      "sourceDate": "2021-07-28"
    },
    {
      "date": "2017-03-01",
      "value": 2.93040293040292,
      "sourceDate": "2021-07-28"
    },
    {
      "date": "2017-04-01",
      "value": 2.7757487216946597,
      "sourceDate": "2021-07-28"
    },
    {
      "date": "2017-05-01",
      "value": 2.036363636363636,
      "sourceDate": "2021-07-28"
    },
    {
      "date": "2017-06-01",
      "value": 1.8840579710144967,
      "sourceDate": "2021-07-28"
    },
    {
      "date": "2017-07-01",
      "value": 0.9386281588447787,
      "sourceDate": "2021-07-28"
    },
    {
      "date": "2017-08-01",
      "value": 0.9372746935832899,
      "sourceDate": "2021-07-28"
    },
    {
      "date": "2017-09-01",
      "value": 0.8639308855291405,
      "sourceDate": "2021-07-28"
    },
    {
      "date": "2017-10-01",
      "value": 0.7168458781362075,
      "sourceDate": "2021-07-28"
    },
    {
      "date": "2017-11-01",
      "value": 0.6433166547533897,
      "sourceDate": "2021-07-28"
    },
    {
      "date": "2017-12-01",
      "value": 0.7137758743754441,
      "sourceDate": "2021-07-28"
    },
    {
      "date": "2018-01-01",
      "value": 1.0699001426533572,
      "sourceDate": "2021-07-28"
    },
    {
      "date": "2018-02-01",
      "value": 1.2125534950071515,
      "sourceDate": "2021-07-28"
    },
    {
      "date": "2018-03-01",
      "value": 0.9964412811388046,
      "sourceDate": "2021-07-28"
    },
    {
      "date": "2018-04-01",
      "value": 0.8528784648187848,
      "sourceDate": "2021-07-28"
    },
    {
      "date": "2018-05-01",
      "value": 1.282965074839626,
      "sourceDate": "2021-07-28"
    },
    {
      "date": "2018-06-01",
      "value": 1.2802275960170695,
      "sourceDate": "2021-07-28"
    },
    {
      "date": "2018-07-01",
      "value": 2.0028612303290227,
      "sourceDate": "2021-07-28"
    },
    {
      "date": "2018-08-01",
      "value": 2.0714285714285685,
      "sourceDate": "2021-07-28"
    },
    {
      "date": "2018-09-01",
      "value": 2.21270521056387,
      "sourceDate": "2021-07-28"
    },
    {
      "date": "2018-10-01",
      "value": 2.2775800711743788,
      "sourceDate": "2021-07-28"
    },
    {
      "date": "2018-11-01",
      "value": 2.2017045454545414,
      "sourceDate": "2021-07-28"
    },
    {
      "date": "2018-12-01",
      "value": 2.126151665485465,
      "sourceDate": "2023-06-27"
    },
    {
      "date": "2019-01-01",
      "value": 2.328863796753722,
      "sourceDate": "2021-09-15"
    },
    {
      "date": "2019-02-01",
      "value": 2.5369978858351017,
      "sourceDate": "2021-09-15"
    },
    {
      "date": "2019-03-01",
      "value": 2.748414376321362,
      "sourceDate": "2021-09-15"
    },
    {
      "date": "2019-04-01",
      "value": 3.241719520789288,
      "sourceDate": "2021-09-15"
    },
    {
      "date": "2019-05-01",
      "value": 3.1667839549613053,
      "sourceDate": "2021-09-15"
    },
    {
      "date": "2019-06-01",
      "value": 3.08988764044944,
      "sourceDate": "2021-09-15"
    },
    {
      "date": "2019-07-01",
      "value": 3.295932678821889,
      "sourceDate": "2021-09-15"
    },
    {
      "date": "2019-08-01",
      "value": 3.149055283414981,
      "sourceDate": "2021-09-15"
    },
    {
      "date": "2019-09-01",
      "value": 2.863128491620137,
      "sourceDate": "2021-09-15"
    },
    {
      "date": "2019-10-01",
      "value": 3.201113430758551,
      "sourceDate": "2021-09-15"
    },
    {
      "date": "2019-11-01",
      "value": 3.2661570535093665,
      "sourceDate": "2021-09-15"
    },
    {
      "date": "2019-12-01",
      "value": 3.3310201249132643,
      "sourceDate": "2021-09-15"
    },
    {
      "date": "2020-01-01",
      "value": 2.758620689655178,
      "sourceDate": "2021-09-15"
    },
    {
      "date": "2020-02-01",
      "value": 2.611683848797264,
      "sourceDate": "2021-09-15"
    },
    {
      "date": "2020-03-01",
      "value": 2.400548696844984,
      "sourceDate": "2021-09-15"
    },
    {
      "date": "2020-04-01",
      "value": 1.2969283276450527,
      "sourceDate": "2021-09-15"
    },
    {
      "date": "2020-05-01",
      "value": 0.9549795361528002,
      "sourceDate": "2021-09-15"
    },
    {
      "date": "2020-06-01",
      "value": 1.9754768392370448,
      "sourceDate": "2021-09-15"
    },
    {
      "date": "2020-07-01",
      "value": 1.4935505770536261,
      "sourceDate": "2021-09-15"
    },
    {
      "date": "2020-08-01",
      "value": 1.8995929443690551,
      "sourceDate": "2021-09-15"
    },
    {
      "date": "2020-09-01",
      "value": 2.1724372029870986,
      "sourceDate": "2021-09-15"
    },
    {
      "date": "2020-10-01",
      "value": 2.629804450438278,
      "sourceDate": "2021-09-15"
    },
    {
      "date": "2020-11-01",
      "value": 2.5572005383580176,
      "sourceDate": "2021-09-15"
    },
    {
      "date": "2020-12-01",
      "value": 2.2834116856951026,
      "sourceDate": "2021-09-15"
    },
    {
      "date": "2021-01-01",
      "value": 1.4093959731543482,
      "sourceDate": "2021-09-15"
    },
    {
      "date": "2021-02-01",
      "value": 1.7414601473543234,
      "sourceDate": "2021-09-15"
    },
    {
      "date": "2021-03-01",
      "value": 2.8131279303415857,
      "sourceDate": "2021-09-15"
    },
    {
      "date": "2021-04-01",
      "value": 4.17789757412399,
      "sourceDate": "2021-09-15"
    },
    {
      "date": "2021-05-01",
      "value": 5.202702702702688,
      "sourceDate": "2021-09-15"
    },
    {
      "date": "2021-06-01",
      "value": 4.809619238476959,
      "sourceDate": "2021-09-15"
    },
    {
      "date": "2021-07-01",
      "value": 5.150501672240804,
      "sourceDate": "2021-09-15"
    },
    {
      "date": "2021-08-01",
      "value": 4.793608521970727,
      "sourceDate": "2021-09-15"
    },
    {
      "date": "2021-09-01",
      "value": 5.249169435215961,
      "sourceDate": "2021-10-20"
    },
    {
      "date": "2021-10-01",
      "value": 4.993429697766105,
      "sourceDate": "2021-11-17"
    },
    {
      "date": "2021-11-01",
      "value": 5.31496062992125,
      "sourceDate": "2021-12-15"
    },
    {
      "date": "2021-12-01",
      "value": 6.040709126723565,
      "sourceDate": "2022-01-19"
    },
    {
      "date": "2022-01-01",
      "value": 7.0814030443415055,
      "sourceDate": "2022-02-16"
    },
    {
      "date": "2022-02-01",
      "value": 7.175773535220542,
      "sourceDate": "2022-03-16"
    },
    {
      "date": "2022-03-01",
      "value": 7.361563517915326,
      "sourceDate": "2022-04-20"
    },
    {
      "date": "2022-04-01",
      "value": 7.632600258732225,
      "sourceDate": "2022-06-22"
    },
    {
      "date": "2022-05-01",
      "value": 7.385998715478492,
      "sourceDate": "2022-06-22"
    },
    {
      "date": "2022-06-01",
      "value": 6.692160611854692,
      "sourceDate": "2022-07-20"
    },
    {
      "date": "2022-07-01",
      "value": 7.379134860050907,
      "sourceDate": "2022-08-16"
    },
    {
      "date": "2022-08-01",
      "value": 7.11562897077509,
      "sourceDate": "2022-09-20"
    },
    {
      "date": "2022-09-01",
      "value": 6.944444444444442,
      "sourceDate": "2022-10-19"
    },
    {
      "date": "2022-10-01",
      "value": 6.821026282853548,
      "sourceDate": "2022-11-16"
    },
    {
      "date": "2022-11-01",
      "value": 6.915887850467284,
      "sourceDate": "2022-12-21"
    },
    {
      "date": "2022-12-01",
      "value": 6.5015479876161075,
      "sourceDate": "2023-01-17"
    },
    {
      "date": "2023-01-01",
      "value": 6.79851668726823,
      "sourceDate": "2023-02-21"
    },
    {
      "date": "2023-02-01",
      "value": 6.326781326781306,
      "sourceDate": "2023-03-21"
    },
    {
      "date": "2023-03-01",
      "value": 5.461165048543681,
      "sourceDate": "2023-04-18"
    },
    {
      "date": "2023-04-01",
      "value": 4.567307692307687,
      "sourceDate": "2023-06-27"
    },
    {
      "date": "2023-05-01",
      "value": 4.4258373205741774,
      "sourceDate": "2023-06-27"
    },
    {
      "date": "2023-06-01",
      "value": 4.778972520907998,
      "sourceDate": "2023-07-18"
    },
    {
      "date": "2023-07-01",
      "value": 4.443127962085303,
      "sourceDate": "2023-08-15"
    },
    {
      "date": "2023-08-01",
      "value": 5.100830367734277,
      "sourceDate": "2023-09-19"
    },
    {
      "date": "2023-09-01",
      "value": 4.899645808736697,
      "sourceDate": "2023-10-17"
    },
    {
      "date": "2023-10-01",
      "value": 5.330990041007633,
      "sourceDate": "2023-11-21"
    },
    {
      "date": "2023-11-01",
      "value": 5.011655011655014,
      "sourceDate": "2023-12-19"
    },
    {
      "date": "2023-12-01",
      "value": 5.406976744186043,
      "sourceDate": "2024-01-16"
    },
    {
      "date": "2024-01-01",
      "value": 5.208333333333326,
      "sourceDate": "2024-02-20"
    },
    {
      "date": "2024-02-01",
      "value": 5.430387059503183,
      "sourceDate": "2024-03-19"
    },
    {
      "date": "2024-03-01",
      "value": 5.523590333716921,
      "sourceDate": "2024-04-16"
    },
    {
      "date": "2024-04-01",
      "value": 5.574712643678148,
      "sourceDate": "2024-06-25"
    },
    {
      "date": "2024-05-01",
      "value": 6.071019473081329,
      "sourceDate": "2024-06-25"
    },
    {
      "date": "2024-06-01",
      "value": 5.7582668187001085,
      "sourceDate": "2024-07-16"
    },
    {
      "date": "2024-07-01",
      "value": 5.4452637549631255,
      "sourceDate": "2024-08-20"
    },
    {
      "date": "2024-08-01",
      "value": 5.191873589164797,
      "sourceDate": "2024-09-17"
    },
    {
      "date": "2024-09-01",
      "value": 5.008441193021951,
      "sourceDate": "2024-10-15"
    },
    {
      "date": "2024-10-01",
      "value": 4.3937708565072064,
      "sourceDate": "2024-11-19"
    },
    {
      "date": "2024-11-01",
      "value": 4.384017758046621,
      "sourceDate": "2024-12-17"
    },
    {
      "date": "2024-12-01",
      "value": 4.136789851075573,
      "sourceDate": "2025-01-21"
    },
    {
      "date": "2025-01-01",
      "value": 4.180418041804179,
      "sourceDate": "2025-02-18"
    },
    {
      "date": "2025-02-01",
      "value": 4.0000000000000036,
      "sourceDate": "2025-03-18"
    },
    {
      "date": "2025-03-01",
      "value": 3.435114503816794,
      "sourceDate": "2025-04-15"
    },
    {
      "date": "2025-04-01",
      "value": 3.0484485574306053,
      "sourceDate": "2025-05-20"
    },
    {
      "date": "2025-05-01",
      "value": 2.1058315334773203,
      "sourceDate": "2025-06-24"
    },
    {
      "date": "2025-06-01",
      "value": 2.0485175202156425,
      "sourceDate": "2025-07-15"
    },
    {
      "date": "2025-07-01",
      "value": 2.151694459386766,
      "sourceDate": "2025-08-19"
    },
    {
      "date": "2025-08-01",
      "value": 1.716738197424883,
      "sourceDate": "2025-09-16"
    },
    {
      "date": "2025-09-01",
      "value": 1.5541264737406246,
      "sourceDate": "2025-10-21"
    },
    {
      "date": "2025-10-01",
      "value": 1.1720831113479102,
      "sourceDate": "2025-11-17"
    },
    {
      "date": "2025-11-01",
      "value": 1.1164274322168932,
      "sourceDate": "2025-12-15"
    },
    {
      "date": "2025-12-01",
      "value": 0.6355932203389703,
      "sourceDate": "2026-01-19"
    },
    {
      "date": "2026-01-01",
      "value": 0.10559662090812161,
      "sourceDate": "2026-02-17"
    },
    {
      "date": "2026-02-01",
      "value": -0.26343519494204104,
      "sourceDate": "2026-03-16"
    },
    {
      "date": "2026-03-01",
      "value": 0.10542962572483994,
      "sourceDate": "2026-04-20"
    },
    {
      "date": "2026-04-01",
      "value": 0.15847860538826808,
      "sourceDate": "2026-05-19"
    },
    {
      "date": "2026-05-01",
      "value": 0.15864621893177944,
      "sourceDate": "2026-06-22"
    }
  ],
  "confirmingIndicators": [
    "Real household income and debt service",
    "Provincial energy CPI"
  ],
  "conflictingIndicators": [
    "Regulated-price or exchange-rate effects"
  ],
  "evidenceChecks": [],
  "confidenceLevel": "medium",
  "evidenceLabel": "Contextual indicator",
  "calculation": {
    "formula": "Year-over-year percent change",
    "explanation": "Year-over-year percent change",
    "example": "Latest observation: 0.16 percent at 2026-05."
  },
  "limitations": [
    "Statistics Canada may revise recent and historical observations.",
    "Cross-country definitions differ."
  ],
  "generatedAt": "2026-07-16T10:23:39+00:00"
}
